{"data":[{"type":"hot_list_feed","style_type":"1","id":"0_1724949072.374808","card_id":"Q_665596255","card_label":{"type":"hot","icon":"https://pic2.zhimg.com/80/v2-266e83dbee46dce23b718e0531cb7d3a_1440w.png","night_icon":"https://pic3.zhimg.com/80/v2-c89199839c237b87e52f010bb5e7d773_1440w.png"},"target":{"id":665596255,"title":"美经济学家预警「1万亿美元资金将回流中国，推动人民币或升值10%」，这释放出什么信号？","url":"https://api.zhihu.com/questions/665596255","type":"question","created":1724900895,"answer_count":332,"follower_count":938,"author":{"type":"people","user_type":"people","id":"0","url_token":"","url":"","name":"用户","headline":"","avatar_url":"https://pica.zhimg.com/aadd7b895_s.jpg"},"bound_topic_ids":[922,3858,19800,32904,105508],"comment_count":0,"is_following":false,"excerpt":"“美元微笑理论”创立者、资产管理公司Eurizon SLJ Capital首席执行官史蒂芬·詹（Stephen Jen）近日发表重要预测称，美联储降息或促使中国企业抛售高达1万亿美元的美元计价资产，从而推动人民币升值至多10%。1万亿美元资金将回流中国？美经济学家预警：人民币或升值10%"},"attached_info":"CkAIwcPumtuCjJxtEAMaCTExMDE4NzcxNSCfzL+2BjAAOKoHQAByCTY2NTU5NjI1NXgAqgEJYmlsbGJvYXJk0gEA","detail_text":"812 万热度","trend":0,"debut":false,"children":[{"type":"answer","thumbnail":"https://pic1.zhimg.com/50/v2-7a69708777a4c07a5ff69384d2fa2864_b.jpg"}]},{"type":"hot_list_feed","style_type":"1","id":"1_1724949072.375708","card_id":"Q_665618796","target":{"id":665618796,"title":"华为上半年销售收入 4175 亿元，同比增长 34.3%，每天净赚 3 亿元，如何评价这一业绩？","url":"https://api.zhihu.com/questions/665618796","type":"question","created":1724919693,"answer_count":212,"follower_count":466,"author":{"type":"people","user_type":"people","id":"0","url_token":"","url":"","name":"用户","headline":"","avatar_url":"https://pica.zhimg.com/aadd7b895_s.jpg"},"bound_topic_ids":[5263,21576,169703,1328765,2136385],"comment_count":0,"is_following":false,"excerpt":"8月29日，华为发布上半年经营业绩。2024年上半年公司实现销售收入4175亿人民币，同比增长34.3%，净利润率13.2%。 华为轮值董事长徐直军表示：“集团整体经营情况符合预期。我们将贯彻全流程‘高质量’的公司战略，持续优化产业组合，增强发展韧性，建设繁荣产业生态，为客户贡献更有竞争力的产品和解决方案。”华为2024年上半年销售收入4175亿人民币，同比增长34.3%|界面新闻 · 快讯"},"attached_info":"CkAIwcPumtuCjJxtEAMaCTExMDE5Mjc1MiCN38C2BjAAONIDQAFyCTY2NTYxODc5NngAqgEJYmlsbGJvYXJk0gEA","detail_text":"481 万热度","trend":0,"debut":false,"children":[{"type":"answer","thumbnail":"https://pica.zhimg.com/80/v2-8d11b3aa7ff9b8bef4203557bcba3f50_720w.png"}]},{"type":"hot_list_feed","style_type":"1","id":"2_1724949072.376302","card_id":"Q_665615785","target":{"id":665615785,"title":"广州首套房贷利率「卷」至 2.89% ，与公积金贷款利率的 2.85% 相差无几，释放了什么信号？","url":"https://api.zhihu.com/questions/665615785","type":"question","created":1724917539,"answer_count":69,"follower_count":220,"author":{"type":"people","user_type":"people","id":"0","url_token":"","url":"","name":"用户","headline":"","avatar_url":"https://pica.zhimg.com/aadd7b895_s.jpg"},"bound_topic_ids":[395,1708,3865,19800,105508],"comment_count":0,"is_following":false,"excerpt":"每经AI快讯，房贷利率价格“感人”，自LPR年内第二次调整后，个人住房商业贷款利率持续下降，不少城市部分银行从“3.0版本”步入“2.0版本”。目前一线城市中，广州首套房贷利率最低已经可以做到2.89%，该利率水平已经与公积金贷款利率的2.85%相差无几。（21财经）再创新低！广州首套房贷利率“卷”至2.89% | 每经网"},"attached_info":"CkAIwcPumtuCjJxtEAMaCTExMDE5MjA3MyCjzsC2BjAAONwBQAJyCTY2NTYxNTc4NXgAqgEJYmlsbGJvYXJk0gEA","detail_text":"154 万热度","trend":0,"debut":false,"children":[{"type":"answer","thumbnail":"https://pic1.zhimg.com/50/v2-751d83ed75a763cdf35719c191284d80_b.jpg"}]},{"type":"hot_list_feed","style_type":"1","id":"3_1724949072.376933","card_id":"Q_665629305","card_label":{"type":"hot","icon":"https://pic2.zhimg.com/80/v2-266e83dbee46dce23b718e0531cb7d3a_1440w.png","night_icon":"https://pic3.zhimg.com/80/v2-c89199839c237b87e52f010bb5e7d773_1440w.png"},"target":{"id":665629305,"title":"中国美院教授酒后涉嫌强奸女研究生，警方对其立案调查，学校回应将从严处理，具体情况如何？","url":"https://api.zhihu.com/questions/665629305","type":"question","created":1724927385,"answer_count":24,"follower_count":59,"author":{"type":"people","user_type":"people","id":"0","url_token":"","url":"","name":"用户","headline":"","avatar_url":"https://pica.zhimg.com/aadd7b895_s.jpg"},"bound_topic_ids":[131,215,27830,44237,47572],"comment_count":0,"is_following":false,"excerpt":"杭州警方通报“中国美院教授涉嫌强奸女研究生”：已刑拘 最新进展 公开资料显示，赵某某，今年59岁，现为中国美术学院书法学院教授，博士生导师，任中国书法家协会楷书专业委员会委员等职。"},"attached_info":"Cj8IwcPumtuCjJxtEAMaCTExMDE5NTEyNCCZm8G2BjAAODtAA3IJNjY1NjI5MzA1eACqAQliaWxsYm9hcmTSAQA=","detail_text":"135 万热度","trend":0,"debut":true,"children":[{"type":"answer","thumbnail":"https://pic2.zhimg.com/50/v2-d112289e0c92247ab1492efeba433581_b.jpg"}]},{"type":"hot_list_feed","style_type":"1","id":"4_1724949072.377340","card_id":"Q_665543358","card_label":{"type":"hot","icon":"https://pic2.zhimg.com/80/v2-266e83dbee46dce23b718e0531cb7d3a_1440w.png","night_icon":"https://pic3.zhimg.com/80/v2-c89199839c237b87e52f010bb5e7d773_1440w.png"},"target":{"id":665543358,"title":"网友曝货车拉烂苹果到礼泉一果汁厂，厂商称原料不良率过高会退回，当地市监局称已取样送检，具体情况如何？","url":"https://api.zhihu.com/questions/665543358","type":"question","created":1724844843,"answer_count":43,"follower_count":83,"author":{"type":"people","user_type":"people","id":"0","url_token":"","url":"","name":"用户","headline":"","avatar_url":"https://pica.zhimg.com/aadd7b895_s.jpg"},"bound_topic_ids":[99,215,678,1740,5582],"comment_count":0,"is_following":false,"excerpt":"8月26日，网友王先生发视频称，在陕西咸阳礼泉县发现给食品厂运水果的货车散发出酸臭味。王先生表示，他就住在停靠货车的街道附近，最近上下班经过，都能闻到酸臭味。“味道很刺鼻，今天早上路过，还有七八辆货车停在那里。” 据纵览新闻，该网友提到，连日来，他看到不止一辆装有腐烂苹果的大货车开进这家公司。 值得注意的是，涉事的礼泉安德利果蔬汁有限公司（下称“礼泉安德利”）为知名果汁龙头，A股H股双上市公司，人称“浓缩果汁大王”的烟台北方安德利果汁股份有限公司（简称：安德利/安德利果汁，代码：605198.SH/02218.HK）的重要下属公司。 “味道刺鼻”，多辆货车拉腐烂水果到果汁厂？知名果汁龙头回应，股价下跌！当地市监局：停止经营接受调查 | 每经网"},"attached_info":"Cj8IwcPumtuCjJxtEAMaCTExMDE3NTk4OSCrlry2BjAAOFNABHIJNjY1NTQzMzU4eACqAQliaWxsYm9hcmTSAQA=","detail_text":"129 万热度","trend":0,"debut":true,"children":[{"type":"answer","thumbnail":"https://pic2.zhimg.com/50/v2-7dce4c77ae1fb6545c5edc5fd2a5eb39_b.jpg"}]},{"type":"hot_list_feed","style_type":"1","id":"5_1724949072.377914","card_id":"Q_665508398","card_label":{"type":"hot","icon":"https://pic2.zhimg.com/80/v2-266e83dbee46dce23b718e0531cb7d3a_1440w.png","night_icon":"https://pic3.zhimg.com/80/v2-c89199839c237b87e52f010bb5e7d773_1440w.png"},"target":{"id":665508398,"title":"如何评价2024年8月米哈游《原神》纳塔5.0上半卡池，玛拉妮和万叶？","url":"https://api.zhihu.com/questions/665508398","type":"question","created":1724815034,"answer_count":39,"follower_count":46,"author":{"type":"people","user_type":"people","id":"0","url_token":"","url":"","name":"用户","headline":"","avatar_url":"https://pica.zhimg.com/aadd7b895_s.jpg"},"bound_topic_ids":[166361,377012,406546,2090987,3588571],"comment_count":0,"is_following":false,"excerpt":"[2 张图片]"},"attached_info":"Cj8IwcPumtuCjJxtEAMaCTExMDE2ODE2OCC6rbq2BjAAOC5ABXIJNjY1NTA4Mzk4eACqAQliaWxsYm9hcmTSAQA=","detail_text":"116 万热度","trend":0,"debut":true,"children":[{"type":"answer","thumbnail":""}]},{"type":"hot_list_feed","style_type":"1","id":"6_1724949072.378339","card_id":"Q_665413822","card_label":{"type":"hot","icon":"https://pic2.zhimg.com/80/v2-266e83dbee46dce23b718e0531cb7d3a_1440w.png","night_icon":"https://pic3.zhimg.com/80/v2-c89199839c237b87e52f010bb5e7d773_1440w.png"},"target":{"id":665413822,"title":"韩议员称「我们的先辈是日本国籍」，在野党议员离席退场抗议，如何评价此议员的言论？","url":"https://api.zhihu.com/questions/665413822","type":"question","created":1724726875,"answer_count":51,"follower_count":80,"author":{"type":"people","user_type":"people","id":"0","url_token":"","url":"","name":"用户","headline":"","avatar_url":"https://pica.zhimg.com/aadd7b895_s.jpg"},"bound_topic_ids":[229,1169,4621,105508,2395667],"comment_count":0,"is_following":false,"excerpt":"【环球网报道】据韩联社报道，在26日韩国国会任命听证会上，被韩国总统尹锡悦提名为新任雇佣劳动部长候选人的金文洙在答辩时宣称，朝鲜半岛被日本殖民统治时期，我们的先辈“是日本国籍”，引发在野党议员的强烈反对，导致任命听证会中断。 据报道，金文洙多年前曾在演讲中主张，对于韩国来说，被日本殖民统治时期“不存在国家”。在26日的任命听证会上，在野党议员就金文洙关于历史问题的言论提出质询，金文洙在答辩时宣称，他现在的想法依旧没有改变，“国家都毁灭了哪来的国籍？”被问及“我们的先辈是日本国籍还是韩国国籍”时，他声称是“日本”。 韩联社称，金文洙的历史观引发在野党议员的强烈反对，共同民主党方面表示，金文洙的言论是“对大韩民国宪法的否认”，并向提名金文洙的尹锡悦总统表示“强烈遗憾”，要求金文洙辞退提名。作为对金文洙言论的抗议，在野党议员纷纷离席退场，导致任命听证会被迫中断。韩媒：尹锡悦政府候任部长答辩时宣称“我们的先辈是日本国籍”，在野党议员离席退场抗议_金文"},"attached_info":"Cj8IwcPumtuCjJxtEAMaCTExMDE0NzMwMiDb/LS2BjAAOFBABnIJNjY1NDEzODIyeACqAQliaWxsYm9hcmTSAQA=","detail_text":"108 万热度","trend":0,"debut":true,"children":[{"type":"answer","thumbnail":"https://pic1.zhimg.com/50/v2-22e130bdace2d90110935de562677a8c_b.jpg"}]},{"type":"hot_list_feed","style_type":"1","id":"7_1724949072.379723","card_id":"Q_665518702","card_label":{"type":"hot","icon":"https://pic2.zhimg.com/80/v2-266e83dbee46dce23b718e0531cb7d3a_1440w.png","night_icon":"https://pic3.zhimg.com/80/v2-c89199839c237b87e52f010bb5e7d773_1440w.png"},"target":{"id":665518702,"title":"伊朗最高领袖暗示与美国恢复伊核谈判，表示与「敌人」接触「没有坏处」，如何解读该表态？","url":"https://api.zhihu.com/questions/665518702","type":"question","created":1724825081,"answer_count":39,"follower_count":58,"author":{"type":"people","user_type":"people","id":"0","url_token":"","url":"","name":"用户","headline":"","avatar_url":"https://pica.zhimg.com/aadd7b895_s.jpg"},"bound_topic_ids":[472,5560,41171,161569,2187155],"comment_count":0,"is_following":false,"excerpt":"【文/观察者网 杨蓉】“伊朗最高领导人为与美国就核计划展开谈判打开大门”，据美联社8月27日报道，伊朗最高领袖哈梅内伊当天会见新一届政府内阁时暗示，伊朗可能与美国恢复伊核协议履约谈判，称伊朗政府与“敌人”接触“没有坏处”。 \t 按照伊朗最高领袖办公室发布的讲话稿，哈梅内伊27日向新任伊朗总统佩泽希齐扬及其内阁强调了不依赖“伊朗敌人”或等待其批准的重要性。“当然，这并不意味着我们不能在某些情况下与同一个敌人互动，这样做没有坏处。”他补充，“但不要把希望寄托在他们身上，不要相信敌人。” \t8月27日，哈梅内伊接见伊朗新一届政府内阁哈梅内伊办公室 “伊朗最高领袖暗示与美国恢复伊核谈判”"},"attached_info":"Cj8IwcPumtuCjJxtEAMaCTExMDE3MDQ2MyD5+7q2BjAAODpAB3IJNjY1NTE4NzAyeACqAQliaWxsYm9hcmTSAQA=","detail_text":"98 万热度","trend":0,"debut":true,"children":[{"type":"answer","thumbnail":"https://pic3.zhimg.com/50/v2-15729349ada8a01f28709a3a10ef646e_b.jpg"}]},{"type":"hot_list_feed","style_type":"1","id":"8_1724949072.380715","card_id":"Q_664923269","card_label":{"type":"hot","icon":"https://pic2.zhimg.com/80/v2-266e83dbee46dce23b718e0531cb7d3a_1440w.png","night_icon":"https://pic3.zhimg.com/80/v2-c89199839c237b87e52f010bb5e7d773_1440w.png"},"target":{"id":664923269,"title":"东北有哪些好吃的饺子馅料呢？","url":"https://api.zhihu.com/questions/664923269","type":"question","created":1724240014,"answer_count":50,"follower_count":109,"author":{"type":"people","user_type":"people","id":"0","url_token":"","url":"","name":"用户","headline":"","avatar_url":"https://pica.zhimg.com/aadd7b895_s.jpg"},"bound_topic_ids":[304,532,5631,18619,281766],"comment_count":0,"is_following":false,"excerpt":""},"attached_info":"Cj8IwcPumtuCjJxtEAMaCTExMDAzODI2NiCOoZe2BjAAOG1ACHIJNjY0OTIzMjY5eACqAQliaWxsYm9hcmTSAQA=","detail_text":"92 万热度","trend":0,"debut":true,"children":[{"type":"answer","thumbnail":"https://pic2.zhimg.com/50/v2-10efcc00bb8167f848401b1db3bf83f9_b.jpg"}]},{"type":"hot_list_feed","style_type":"1","id":"9_1724949072.380929","card_id":"Q_665598504","card_label":{"type":"hot","icon":"https://pic2.zhimg.com/80/v2-266e83dbee46dce23b718e0531cb7d3a_1440w.png","night_icon":"https://pic3.zhimg.com/80/v2-c89199839c237b87e52f010bb5e7d773_1440w.png"},"target":{"id":665598504,"title":"《黑神话：悟空》爆火后我有个疑问，什么算 3A 游戏？是谁来负责评定？","url":"https://api.zhihu.com/questions/665598504","type":"question","created":1724902677,"answer_count":24,"follower_count":28,"author":{"type":"people","user_type":"people","id":"0","url_token":"","url":"","name":"用户","headline":"","avatar_url":"https://pica.zhimg.com/aadd7b895_s.jpg"},"bound_topic_ids":[253,284,224070,601256],"comment_count":0,"is_following":false,"excerpt":"百科介绍： AAA游戏（Triple-A games），也称为3A游戏，为电子游戏产业中的一个分野，没有准确定义，一般认为是指投入高制作费用与高营销成本的游戏[1][2][3][4]。其中营销成本也是巨大的开销，宣传费用甚至可能超过制作游戏本身的花费[5]。根据inXile娱乐CEO Brian Fargo的访谈，以相对AAA低一阶的AA级游戏来说，在2018年仅以制作费用估量，AA级的上限已达到2000万美元水准[6]；由上述数字可知，AAA级游戏的制作费用无疑是一笔相对更高的巨额投资。根据前索尼互动娱乐CEO Shawn Layden的访谈，就2020年市场中的大多数AAA级游戏来看，仅估算制作费用已达8000万至1亿5000万美元的水准，并需要长达5年的游戏制作时间[7]。"},"attached_info":"Cj8IwcPumtuCjJxtEAMaCTExMDE4ODIxOCCV2r+2BjAAOBxACXIJNjY1NTk4NTA0eACqAQliaWxsYm9hcmTSAQA=","detail_text":"73 万热度","trend":0,"debut":true,"children":[{"type":"answer","thumbnail":"https://pic3.zhimg.com/50/v2-9a53f21d9e05f05ba4c449ae37951496_b.jpg"}]},{"type":"hot_list_feed","style_type":"1","id":"10_1724949072.381433","card_id":"Q_665517571","card_label":{"type":"hot","icon":"https://pic2.zhimg.com/80/v2-266e83dbee46dce23b718e0531cb7d3a_1440w.png","night_icon":"https://pic3.zhimg.com/80/v2-c89199839c237b87e52f010bb5e7d773_1440w.png"},"target":{"id":665517571,"title":"常务副局长是普通副局长的领导吗？","url":"https://api.zhihu.com/questions/665517571","type":"question","created":1724824091,"answer_count":29,"follower_count":35,"author":{"type":"people","user_type":"people","id":"0","url_token":"","url":"","name":"用户","headline":"","avatar_url":"https://pica.zhimg.com/aadd7b895_s.jpg"},"bound_topic_ids":[3226],"comment_count":0,"is_following":false,"excerpt":"县住建局常务副局长（正科级，一级主任科员），县住建局普通副局长（副科级），见到常务副职需要叫领导吗？"},"attached_info":"Cj8IwcPumtuCjJxtEAMaCTExMDE3MDIxNiCb9Lq2BjAAOCNACnIJNjY1NTE3NTcxeACqAQliaWxsYm9hcmTSAQA=","detail_text":"70 万热度","trend":0,"debut":true,"children":[{"type":"answer","thumbnail":""}]},{"type":"hot_list_feed","style_type":"1","id":"11_1724949072.381814","card_id":"Q_665319877","card_label":{"type":"new","icon":"https://pic2.zhimg.com/80/v2-a4b0b52b561281109c51e4957cb20130_1440w.png","night_icon":"https://pic3.zhimg.com/80/v2-10ef6526c602e55a8c606e46aa0cc586_1440w.png"},"target":{"id":665319877,"title":"有哪些受益终身的忠告？","url":"https://api.zhihu.com/questions/665319877","type":"question","created":1724639651,"answer_count":91,"follower_count":118,"author":{"type":"people","user_type":"people","id":"0","url_token":"","url":"","name":"用户","headline":"","avatar_url":"https://pica.zhimg.com/aadd7b895_s.jpg"},"bound_topic_ids":[2099111],"comment_count":0,"is_following":false,"excerpt":""},"attached_info":"Cj8IwcPumtuCjJxtEAMaCTExMDEyNjQ3MyCj06+2BjAAOHZAC3IJNjY1MzE5ODc3eACqAQliaWxsYm9hcmTSAQA=","detail_text":"67 万热度","trend":0,"debut":true,"children":[{"type":"answer","thumbnail":"https://pic4.zhimg.com/50/v2-0b3f296c2fb4ab9b9101bafeaa2f90f7_b.jpg"}]},{"type":"hot_list_feed","style_type":"1","id":"12_1724949072.382096","card_id":"Q_660621004","card_label":{"type":"hot","icon":"https://pic2.zhimg.com/80/v2-266e83dbee46dce23b718e0531cb7d3a_1440w.png","night_icon":"https://pic3.zhimg.com/80/v2-c89199839c237b87e52f010bb5e7d773_1440w.png"},"target":{"id":660621004,"title":"现在孩子的暑假和你小时候的暑假有什么不一样？","url":"https://api.zhihu.com/questions/660621004","type":"question","created":1719993200,"answer_count":227,"follower_count":296,"author":{"type":"people","user_type":"people","id":"0","url_token":"","url":"","name":"用户","headline":"","avatar_url":"https://pica.zhimg.com/aadd7b895_s.jpg"},"bound_topic_ids":[1395,3412,17883,65149,3586093],"comment_count":0,"is_following":false,"excerpt":""},"attached_info":"CkAIwcPumtuCjJxtEAMaCTEwOTA4MjI3OCDwhpS0BjAAOKgCQAxyCTY2MDYyMTAwNHgAqgEJYmlsbGJvYXJk0gEA","detail_text":"58 万热度","trend":0,"debut":false,"children":[{"type":"answer","thumbnail":"https://pic3.zhimg.com/50/v2-c2aacbc4839cc349d4226872c0d7315e_b.jpg"}]},{"type":"hot_list_feed","style_type":"1","id":"13_1724949072.382427","card_id":"Q_646932087","card_label":{"type":"hot","icon":"https://pic2.zhimg.com/80/v2-266e83dbee46dce23b718e0531cb7d3a_1440w.png","night_icon":"https://pic3.zhimg.com/80/v2-c89199839c237b87e52f010bb5e7d773_1440w.png"},"target":{"id":646932087,"title":"为什么好产品经理极度稀缺？","url":"https://api.zhihu.com/questions/646932087","type":"question","created":1709500847,"answer_count":173,"follower_count":565,"author":{"type":"people","user_type":"people","id":"0","url_token":"","url":"","name":"用户","headline":"","avatar_url":"https://pica.zhimg.com/aadd7b895_s.jpg"},"bound_topic_ids":[99,368,639],"comment_count":0,"is_following":false,"excerpt":""},"attached_info":"CkAIwcPumtuCjJxtEAMaCTEwNjA0MDA0NiCv05OvBjAAOLUEQA1yCTY0NjkzMjA4N3gAqgEJYmlsbGJvYXJk0gEA","detail_text":"57 万热度","trend":0,"debut":true,"children":[{"type":"answer","thumbnail":"https://picx.zhimg.com/80/v2-3958263f0f78b6aa1bbec528fb8748a3_720w.png"}]},{"type":"hot_list_feed","style_type":"1","id":"14_1724949072.382709","card_id":"Q_665519671","target":{"id":665519671,"title":"夫妻已有二孩再生四胞胎，父亲称「希望社会能给予一些帮助，压力特别大」，如何看待此事？","url":"https://api.zhihu.com/questions/665519671","type":"question","created":1724825784,"answer_count":226,"follower_count":340,"author":{"type":"people","user_type":"people","id":"0","url_token":"","url":"","name":"用户","headline":"","avatar_url":"https://pica.zhimg.com/aadd7b895_s.jpg"},"bound_topic_ids":[1489,1939,5582,6086,183254],"comment_count":0,"is_following":false,"excerpt":"8月23日，已有二孩的产妇李女士在深圳成功诞下四胞胎，从原本温馨的四口之家，瞬间扩容为热闹非凡的八口之家。一家人虽然很开心，但同时又感到压力山大…养育孩子的成本对于本就不太宽裕的家庭来说，成了一大难题。 四胞胎早产 孕妈身体恢复良好 距离预产期还有一个多月，李女士的四胞胎就迫不及待地提前来到这个世界。由于是早产儿，四胞胎刚刚出生没多久，就住进了市妇幼新生儿重症监护室。 在医护人员的悉心照料下，最近几天，四胞胎状态好了很多。监护室外，母亲李霞的身体也在逐步恢复。 四胞胎父亲陈先生介绍说，今年一月份发现妻子怀孕，三月份检查出四胞胎。医院征求陈先生和李女士意见，夫妻二人充分考虑后，还是决定生下这四个孩子。 四胞胎母亲李霞称：“身体恢复得还行，心情比较激动，就是担心经济上面的压力。” 四胞胎母亲 李霞 四胞胎父亲陈小波表示：“当时是很高兴很开心，但是高兴之余，也有忧愁。孩子生下来之后怎么抚养，是个很大的难题。” 四胞胎父亲 陈小波 监护室需治疗一个月 20万元费用让夫妻发愁 新添了四件小棉袄的陈先生既兴奋又焦虑。目前，四个孩子需要在重症监护室治疗一个月，预计需要20万元的费用。虽然之后这笔费用可以在户籍所在地社保报销80%，可眼下陈先生夫妇怎么也拿不出这笔钱。 医院考虑到这家人处境困难，也提供了帮助。 深圳市妇幼保健院福强院区产科主任秦微称：“我们医院已经为孕产妇提供了优质的医疗和护理服务，同时我们的社工部已经介入，会在能力范围尽可能提供帮助。” 市妇联介绍，陈先生还可以每年申请贫困妇女儿童救助金最高2000元。据陈先生说，他和妻子都在龙华一家公司就职，每月收入加在一起，共有一万元左右。 原先家里已有两个孩子，四胞胎出生后，为了能够照顾六个孩子，陈先生的妻子不得不辞掉自己的工作。家庭的经济重担，就全落在了陈先生的肩头。 四胞胎父亲陈小波表示：“我是一个打工族，收入方面比较微薄。如果后面养孩子有大量的支出，对于我们家庭来说会比较困难。希望社会能给予一些帮助，我真的是没办法了，生活压力特别大。” （来源：第一现场）二孩夫妻又生四胞胎，孩子父亲：夫妻月收入约1万，妻子辞职后养6个孩子压力特别大_陈先生_陈小波_家庭"},"attached_info":"CkAIwcPumtuCjJxtEAMaCTExMDE3MDY4OSC4gbu2BjAAONQCQA5yCTY2NTUxOTY3MXgAqgEJYmlsbGJvYXJk0gEA","detail_text":"54 万热度","trend":0,"debut":false,"children":[{"type":"answer","thumbnail":"https://pic2.zhimg.com/v2-6446705e95992524f4de1389dfe02cd5_b.jpg"}]},{"type":"hot_list_feed","style_type":"1","id":"15_1724949072.385091","card_id":"Q_665552440","target":{"id":665552440,"title":"杭州警方通报「网红雪梨被指涉毒」，称样本检测均为阴性，如何看待此次风波？","url":"https://api.zhihu.com/questions/665552440","type":"question","created":1724854990,"answer_count":113,"follower_count":278,"author":{"type":"people","user_type":"people","id":"0","url_token":"","url":"","name":"用户","headline":"","avatar_url":"https://pica.zhimg.com/aadd7b895_s.jpg"},"bound_topic_ids":[215,2879,13572,105702,3685420],"comment_count":0,"is_following":false,"excerpt":"网红雪梨被指涉毒，杭州警方通报_腾讯新闻"},"attached_info":"CkAIwcPumtuCjJxtEAMaCTExMDE3ODAwMiDO5by2BjAAOJYCQA9yCTY2NTU1MjQ0MHgAqgEJYmlsbGJvYXJk0gEA","detail_text":"50 万热度","trend":0,"debut":false,"children":[{"type":"answer","thumbnail":"https://pic1.zhimg.com/50/v2-19c20ecf123b8c28bec76cfccc983478_b.jpg"}]},{"type":"hot_list_feed","style_type":"1","id":"16_1724949072.385451","card_id":"Q_665547644","target":{"id":665547644,"title":"开战之前，俄罗斯高层不清楚俄乌双方实力吗？没预料过仗会打成这样吗？","url":"https://api.zhihu.com/questions/665547644","type":"question","created":1724849683,"answer_count":194,"follower_count":353,"author":{"type":"people","user_type":"people","id":"0","url_token":"","url":"","name":"用户","headline":"","avatar_url":"https://pica.zhimg.com/aadd7b895_s.jpg"},"bound_topic_ids":[34688,136525,1987617,2002924,2469868],"comment_count":0,"is_following":false,"excerpt":""},"attached_info":"CkAIwcPumtuCjJxtEAMaCTExMDE3Njk1NSCTvLy2BjAAOOECQBByCTY2NTU0NzY0NHgAqgEJYmlsbGJvYXJk0gEA","detail_text":"50 万热度","trend":0,"debut":false,"children":[{"type":"answer","thumbnail":"https://pic1.zhimg.com/50/v2-50ba44119952c02809bba305b27ad10c_b.jpg"}]},{"type":"hot_list_feed","style_type":"1","id":"17_1724949072.385693","card_id":"Q_661789355","target":{"id":661789355,"title":"马超在历史上是怎么样的一个人？为什么他在刘备集团得不到重用？","url":"https://api.zhihu.com/questions/661789355","type":"question","created":1721142659,"answer_count":23,"follower_count":46,"author":{"type":"people","user_type":"people","id":"0","url_token":"","url":"","name":"用户","headline":"","avatar_url":"https://pica.zhimg.com/aadd7b895_s.jpg"},"bound_topic_ids":[284,3676,3679,139513,140956],"comment_count":0,"is_following":false,"excerpt":"如题。"},"attached_info":"Cj8IwcPumtuCjJxtEAMaCTEwOTM0MjE2NCCDm9q0BjAAOC5AEXIJNjYxNzg5MzU1eACqAQliaWxsYm9hcmTSAQA=","detail_text":"50 万热度","trend":0,"debut":true,"children":[{"type":"answer","thumbnail":"https://pic3.zhimg.com/50/v2-f6b56e629dd62d67754bf5ef2c43f4ea_b.jpg"}]},{"type":"hot_list_feed","style_type":"1","id":"18_1724949072.386017","card_id":"Q_664868918","target":{"id":664868918,"title":"《黑神话：悟空》成功后，你们最期待下一部 3A 是什么题材？","url":"https://api.zhihu.com/questions/664868918","type":"question","created":1724205691,"answer_count":1849,"follower_count":2037,"author":{"type":"people","user_type":"people","id":"0","url_token":"","url":"","name":"用户","headline":"","avatar_url":"https://pica.zhimg.com/aadd7b895_s.jpg"},"bound_topic_ids":[601256],"comment_count":0,"is_following":false,"excerpt":""},"attached_info":"CkAIwcPumtuCjJxtEAMaCTExMDAyNjE0MSD7lJW2BjAAOPUPQBJyCTY2NDg2ODkxOHgAqgEJYmlsbGJvYXJk0gEA","detail_text":"49 万热度","trend":0,"debut":false,"children":[{"type":"answer","thumbnail":"https://pic2.zhimg.com/v2-deec48ebe4e6a5ee70ca9f4532e18cb5_b.jpg"}]},{"type":"hot_list_feed","style_type":"1","id":"19_1724949072.386249","card_id":"Q_658574900","target":{"id":658574900,"title":"如果沙瑞金刚到汉东，高育良主动向沙瑞金坦白一切，能免去牢狱之灾呢？","url":"https://api.zhihu.com/questions/658574900","type":"question","created":1718024645,"answer_count":81,"follower_count":141,"author":{"type":"people","user_type":"people","id":"0","url_token":"","url":"","name":"用户","headline":"","avatar_url":"https://pica.zhimg.com/aadd7b895_s.jpg"},"bound_topic_ids":[3226,168206],"comment_count":0,"is_following":false,"excerpt":""},"attached_info":"CkAIwcPumtuCjJxtEAMaCTEwODYyODA1NyDF85uzBjAAOI0BQBNyCTY1ODU3NDkwMHgAqgEJYmlsbGJvYXJk0gEA","detail_text":"46 万热度","trend":0,"debut":false,"children":[{"type":"answer","thumbnail":"https://pic4.zhimg.com/50/v2-113a7f5a986d34f69b5ba995a3bda23b_b.jpg"}]},{"type":"hot_list_feed","style_type":"1","id":"20_1724949072.386569","card_id":"Q_617687905","target":{"id":617687905,"title":"孙悟空和白骨精是怎么组成cp的？","url":"https://api.zhihu.com/questions/617687905","type":"question","created":1692207800,"answer_count":36,"follower_count":69,"author":{"type":"people","user_type":"people","id":"0","url_token":"","url":"","name":"用户","headline":"","avatar_url":"https://pica.zhimg.com/aadd7b895_s.jpg"},"bound_topic_ids":[2279,10867,156312,172221],"comment_count":0,"is_following":false,"excerpt":"很疑惑白骨精在原著里明明是存在感极低的一个妖精，但她和孙悟空的同人故事还挺多的，这是为什么？"},"attached_info":"Cj4IwcPumtuCjJxtEAMaCDk5NTQ0MTk3ILiV9KYGMAA4RUAUcgk2MTc2ODc5MDV4AKoBCWJpbGxib2FyZNIBAA==","detail_text":"37 万热度","trend":0,"debut":false,"children":[{"type":"answer","thumbnail":"https://pic3.zhimg.com/50/v2-d9a91118d1939605b59762b2596af5e6_b.jpg"}]},{"type":"hot_list_feed","style_type":"1","id":"21_1724949072.386854","card_id":"Q_551114708","target":{"id":551114708,"title":"《地下交通站》里黑藤怀疑鼎香楼，为什么不直接下手还要找证据？","url":"https://api.zhihu.com/questions/551114708","type":"question","created":1661992241,"answer_count":125,"follower_count":253,"author":{"type":"people","user_type":"people","id":"0","url_token":"","url":"","name":"用户","headline":"","avatar_url":"https://pica.zhimg.com/aadd7b895_s.jpg"},"bound_topic_ids":[211353],"comment_count":0,"is_following":false,"excerpt":"黑藤不能直接派侦缉队抓走鼎香楼众人，然后直接捣毁鼎香楼确保万一吗？为什么还得多番调查寻找证据？"},"attached_info":"Cj8IwcPumtuCjJxtEAMaCDg0NzUzNzcwILH6v5gGMAA4/QFAFXIJNTUxMTE0NzA4eACqAQliaWxsYm9hcmTSAQA=","detail_text":"34 万热度","trend":0,"debut":false,"children":[{"type":"answer","thumbnail":"https://picx.zhimg.com/80/v2-1da3d7aab778963317158adbb3e7517a_720w.png"}]},{"type":"hot_list_feed","style_type":"1","id":"22_1724949072.387114","card_id":"Q_662584014","target":{"id":662584014,"title":"如果《卡拉马佐夫兄弟》能写完，能否超越《安娜卡列尼娜》?","url":"https://api.zhihu.com/questions/662584014","type":"question","created":1721920212,"answer_count":36,"follower_count":148,"author":{"type":"people","user_type":"people","id":"0","url_token":"","url":"","name":"用户","headline":"","avatar_url":"https://pica.zhimg.com/aadd7b895_s.jpg"},"bound_topic_ids":[2058,21621,37405,191542,193707],"comment_count":0,"is_following":false,"excerpt":""},"attached_info":"CkAIwcPumtuCjJxtEAMaCTEwOTUxODczMSDU1Ym1BjAAOJQBQBZyCTY2MjU4NDAxNHgAqgEJYmlsbGJvYXJk0gEA","detail_text":"25 万热度","trend":0,"debut":false,"children":[{"type":"answer","thumbnail":"https://picx.zhimg.com/80/v2-0ad1bac437f2997b1a6e1abf1ba512c4_720w.png"}]},{"type":"hot_list_feed","style_type":"1","id":"23_1724949072.387291","card_id":"Q_664966642","target":{"id":664966642,"title":"做了很多细致的计划，但做完计划就感到「满足」了，缺少实行的执行力怎么办？","url":"https://api.zhihu.com/questions/664966642","type":"question","created":1724259825,"answer_count":41,"follower_count":112,"author":{"type":"people","user_type":"people","id":"0","url_token":"","url":"","name":"用户","headline":"","avatar_url":"https://pica.zhimg.com/aadd7b895_s.jpg"},"bound_topic_ids":[404,823,17566,19907,37091],"comment_count":0,"is_following":false,"excerpt":""},"attached_info":"Cj8IwcPumtuCjJxtEAMaCTExMDA0Nzg0NyDxu5i2BjAAOHBAF3IJNjY0OTY2NjQyeACqAQliaWxsYm9hcmTSAQA=","detail_text":"10 万热度","trend":0,"debut":false,"children":[{"type":"answer","thumbnail":"https://pica.zhimg.com/80/v2-c77b0b72afcd3220641c2833e41316e8_720w.webp?source=1def8aca"}]},{"type":"hot_list_feed","style_type":"1","id":"24_1724949072.387516","card_id":"Q_665496155","target":{"id":665496155,"title":"如何看待V社今年关于Dota2国际邀请赛取消赞助商展示的决定？","url":"https://api.zhihu.com/questions/665496155","type":"question","created":1724801324,"answer_count":35,"follower_count":61,"author":{"type":"people","user_type":"people","id":"0","url_token":"","url":"","name":"用户","headline":"","avatar_url":"https://pica.zhimg.com/aadd7b895_s.jpg"},"bound_topic_ids":[2934,29486,168137],"comment_count":0,"is_following":false,"excerpt":"国际邀请赛是为Dota和支持Dota的全球玩家和粉丝举行的庆典，让所有人都有机会齐聚一堂，见证全世界的顶尖队伍奉上最高水平的比赛。 国际邀请赛的核心在于玩家社群——每个制作短片或者制作cosplay服装或者设计T恤的人，每个在观众席（或者沙发上）为最喜爱的战队或英雄呐喊——在于玩家们一起观看的比赛：比赛开始后，重点是比赛本身，还有为了胜利全力以赴的选手们。 多年以来，我们在Dota中加入了很多功能，在庆典中帮助这些战队和选手；遗憾的是，我们也看到这些功能逐渐被用来承载广告内容，而不是展示战队或选手。 今年，为了移除这些分散注意力的元素，让大家完全把注意力放在比赛和参赛的选手身上，我们在今年的国际邀请赛的游戏内不再显示广告和赞助信息，包括战队旗帜，基地标志和选手昵称中的标签。 纯粹刀塔？躺平刀塔？ 今年的大赛还有短短数周的时间就会拉开帷幕。 不论是在丹麦的线下会面，还是线上观赛，我们都将很快见面。"},"attached_info":"Cj8IwcPumtuCjJxtEAMaCTExMDE2NTQ4MyCswrm2BjAAOD1AGHIJNjY1NDk2MTU1eACqAQliaWxsYm9hcmTSAQA=","detail_text":"10 万热度","trend":0,"debut":false,"children":[{"type":"answer","thumbnail":"https://pic1.zhimg.com/80/v2-4903f4851ca771c984fd5ecb3e9c6799_720w.png"}]},{"type":"hot_list_feed","style_type":"1","id":"25_1724949072.388200","card_id":"Q_664105423","target":{"id":664105423,"title":"跑步带手机不方便怎么办？","url":"https://api.zhihu.com/questions/664105423","type":"question","created":1723455182,"answer_count":135,"follower_count":165,"author":{"type":"people","user_type":"people","id":"0","url_token":"","url":"","name":"用户","headline":"","avatar_url":"https://pica.zhimg.com/aadd7b895_s.jpg"},"bound_topic_ids":[844,15836,20167],"comment_count":0,"is_following":false,"excerpt":""},"attached_info":"CkAIwcPumtuCjJxtEAMaCTEwOTg1NjYyMyDOree1BjAAOKUBQBlyCTY2NDEwNTQyM3gAqgEJYmlsbGJvYXJk0gEA","detail_text":"10 万热度","trend":0,"debut":false,"children":[{"type":"answer","thumbnail":"https://pic1.zhimg.com/80/v2-11a95eda96947e9d675167a111cb899e_720w.png"}]},{"type":"hot_list_feed","style_type":"1","id":"26_1724949072.388528","card_id":"Q_45768561","target":{"id":45768561,"title":"如何评价焦恩俊演的二郎神？","url":"https://api.zhihu.com/questions/45768561","type":"question","created":1462714466,"answer_count":474,"follower_count":1100,"author":{"type":"people","user_type":"people","id":"0","url_token":"","url":"","name":"用户","headline":"","avatar_url":"https://pica.zhimg.com/aadd7b895_s.jpg"},"bound_topic_ids":[1818,113770,175743],"comment_count":0,"is_following":false,"excerpt":"焦恩俊在宝莲灯及其前传里饰演的二郎神，有何特色？"},"attached_info":"Cj4IwcPumtuCjJxtEAMaCDEwNTIwMDU3IOKAvbkFMAA4zAhAGnIINDU3Njg1NjF4AKoBCWJpbGxib2FyZNIBAA==","detail_text":"9 万热度","trend":0,"debut":false,"children":[{"type":"answer","thumbnail":"https://picx.zhimg.com/80/ec48c350d57df3311adefedf0bf732bd_1440w.webp?source=1940ef5c"}]},{"type":"hot_list_feed","style_type":"1","id":"27_1724949072.388817","card_id":"Q_665416867","target":{"id":665416867,"title":"为什么 2024 暑期档没有爆剧也没爆人？","url":"https://api.zhihu.com/questions/665416867","type":"question","created":1724729093,"answer_count":21,"follower_count":33,"author":{"type":"people","user_type":"people","id":"0","url_token":"","url":"","name":"用户","headline":"","avatar_url":"https://pica.zhimg.com/aadd7b895_s.jpg"},"bound_topic_ids":[1497,2102,5419,3498261],"comment_count":0,"is_following":false,"excerpt":"去年暑期档起码还有魏大勋算是成功出圈。今年暑期档的《长相思 2》《唐诡 2》还到不了爆剧的地步吧…"},"attached_info":"Cj8IwcPumtuCjJxtEAMaCTExMDE0Nzk3NCCFjrW2BjAAOCFAG3IJNjY1NDE2ODY3eACqAQliaWxsYm9hcmTSAQA=","detail_text":"9 万热度","trend":0,"debut":false,"children":[{"type":"answer","thumbnail":"https://pic4.zhimg.com/50/v2-469d4f4fd32fb5e57f558c87b033c5b7_b.gif"}]},{"type":"hot_list_feed","style_type":"1","id":"28_1724949072.389182","card_id":"Q_662670683","target":{"id":662670683,"title":"美国重新工业化有多难？","url":"https://api.zhihu.com/questions/662670683","type":"question","created":1722006915,"answer_count":123,"follower_count":235,"author":{"type":"people","user_type":"people","id":"0","url_token":"","url":"","name":"用户","headline":"","avatar_url":"https://pica.zhimg.com/aadd7b895_s.jpg"},"bound_topic_ids":[464,472,37082],"comment_count":0,"is_following":false,"excerpt":"美国有三亿人口，有完善的基建，充足的电力供应，还有横跨大西洋，太平洋的绝佳地理位置全球第四大的国土，大量受过高等教育的人才。 更重要的是，有美元，美军，科技，金融主导的世界秩序。"},"attached_info":"CkAIwcPumtuCjJxtEAMaCTEwOTUzNzk3OSCD+461BjAAOOsBQBxyCTY2MjY3MDY4M3gAqgEJYmlsbGJvYXJk0gEA","detail_text":"9 万热度","trend":0,"debut":false,"children":[{"type":"answer","thumbnail":"https://pic3.zhimg.com/50/v2-e2618f2b8dc5223be44df845f309c1ee_b.jpg"}]},{"type":"hot_list_feed","style_type":"1","id":"29_1724949072.389537","card_id":"Q_662639448","target":{"id":662639448,"title":"初入职场，哪种心态能帮助我们更好地应对工作挑战？","url":"https://api.zhihu.com/questions/662639448","type":"question","created":1721979937,"answer_count":41,"follower_count":59,"author":{"type":"people","user_type":"people","id":"0","url_token":"","url":"","name":"用户","headline":"","avatar_url":"https://pica.zhimg.com/aadd7b895_s.jpg"},"bound_topic_ids":[2566,27919,212180,2090874,3539705],"comment_count":0,"is_following":false,"excerpt":""},"attached_info":"Cj8IwcPumtuCjJxtEAMaCTEwOTUzMTA3OCChqI21BjAAODtAHXIJNjYyNjM5NDQ4eACqAQliaWxsYm9hcmTSAQA=","detail_text":"9 万热度","trend":0,"debut":false,"children":[{"type":"answer","thumbnail":"https://pic1.zhimg.com/50/v2-04e07ad0b861cdda8e4ddede4b9f1b94_b.jpg"}]}],"description":{"time":"2024-08-30 00:31:12"}}