{"data":[{"type":"hot_list_feed","style_type":"1","id":"0_1658762809.6298983","card_id":"Q_545240855","target":{"id":545240855,"title":"外交部回应佩洛西拟窜访台湾，称「中方将严阵以待」，如何解读这一表态？","url":"https://api.zhihu.com/questions/545240855","type":"question","created":1658737581,"answer_count":610,"follower_count":1166,"author":{"type":"people","user_type":"people","id":"0","url_token":"","url":"","name":"用户","headline":"","avatar_url":"https://pica.zhimg.com/aadd7b895_s.jpg"},"bound_topic_ids":[1070,2161,23846,33564,587924],"comment_count":53,"is_following":false,"excerpt":"在今天（25日）下午的外交部例行记者会上，有记者就美国众议院议长佩洛西拟于今年8月窜访台湾一事提问。 对此，发言人赵立坚回应时表示，中方已多次就此表明坚决反对和严重关切，中方将严阵以待。 赵立坚强调，美方若一意孤行，中方必将采取坚定有力措施捍卫国家主权和领土完整，由此造成的一切严重后果应由美方负责。 （总台央视记者 朱若梦 杨毅）"},"attached_info":"Cj8Im4Pz3NOd09xaEAMaCDgzNDQ3NDUyIK2n+ZYGMDU4jglAAHIJNTQ1MjQwODU1eACqAQliaWxsYm9hcmTSAQA=","detail_text":"1962 万热度","trend":0,"debut":false,"children":[{"type":"answer","thumbnail":"https://pic2.zhimg.com/80/v2-155e6dd015a0c0ed76b5180455a59174_1440w.jpg?source=1940ef5c"}]},{"type":"hot_list_feed","style_type":"1","id":"1_1658762809.630724","card_id":"Q_544969213","target":{"id":544969213,"title":"如何看待网传华中科技大学计算机学院陈汉华十年博导无一博士毕业?","url":"https://api.zhihu.com/questions/544969213","type":"question","created":1658586832,"answer_count":466,"follower_count":2461,"author":{"type":"people","user_type":"people","id":"0","url_token":"","url":"","name":"用户","headline":"","avatar_url":"https://pica.zhimg.com/aadd7b895_s.jpg"},"bound_topic_ids":[12277,12967,108165,230220,585718],"comment_count":47,"is_following":false,"excerpt":""},"attached_info":"Cj8Im4Pz3NOd09xaEAMaCDgzMzg2OTMzINCN8JYGMC84nRNAAXIJNTQ0OTY5MjEzeACqAQliaWxsYm9hcmTSAQA=","detail_text":"1728 万热度","trend":0,"debut":false,"children":[{"type":"answer","thumbnail":"https://pic1.zhimg.com/80/v2-cee8ce784a0f7b342c67954f162ac8ba_1440w.png"}]},{"type":"hot_list_feed","style_type":"1","id":"2_1658762809.6311874","card_id":"Q_545211115","target":{"id":545211115,"title":"武汉回应「公职人员购房可预发 15 万补贴」，称「未来 5 年内会从收入中扣除」，这意味着什么？","url":"https://api.zhihu.com/questions/545211115","type":"question","created":1658730136,"answer_count":491,"follower_count":1130,"author":{"type":"people","user_type":"people","id":"0","url_token":"","url":"","name":"用户","headline":"","avatar_url":"https://pica.zhimg.com/aadd7b895_s.jpg"},"bound_topic_ids":[1708,3226,3865,5582,105508],"comment_count":57,"is_following":false,"excerpt":"日前一份武汉市东西湖区财政局印发《预发住房分配货币化补贴的方案》的通知在网络流传。该预发补贴方案的主要内容是：属于住房分配货币化补贴政策对象的行政事业单位职工，在方案下发之日起至2022年12月31日前在东西湖区内新购房的，可一次性获预发购房补贴15万元。 对此，武汉市东西湖区财政局一位工作人员表示，这部分补贴为预发放，未来5年内会从收入中进行扣除。 来源：财联社"},"attached_info":"Cj8Im4Pz3NOd09xaEAMaCDgzNDQwODA4IJjt+JYGMDk46ghAAnIJNTQ1MjExMTE1eACqAQliaWxsYm9hcmTSAQA=","detail_text":"1018 万热度","trend":0,"debut":false,"children":[{"type":"answer","thumbnail":"https://picx.zhimg.com/80/v2-e7a57cfe93868a7e520f93d886f84903_1440w.png"}]},{"type":"hot_list_feed","style_type":"1","id":"3_1658762809.6317523","card_id":"Q_35558370","target":{"id":35558370,"title":"乐高为什么无法仿制？","url":"https://api.zhihu.com/questions/35558370","type":"question","created":1442060639,"answer_count":888,"follower_count":2764,"author":{"type":"people","user_type":"people","id":"0","url_token":"","url":"","name":"用户","headline":"","avatar_url":"https://pica.zhimg.com/aadd7b895_s.jpg"},"bound_topic_ids":[1988,14874,572842],"comment_count":60,"is_following":false,"excerpt":"假的玩过 一玩就知道是假的 一个简单的积木以中国人的能力为何无法百分之百仿制出来？"},"attached_info":"Cj0Im4Pz3NOd09xaEAMaBzY0MzAwMzAg37LQrwUwPDjMFUADcggzNTU1ODM3MHgAqgEJYmlsbGJvYXJk0gEA","detail_text":"881 万热度","trend":0,"debut":false,"children":[{"type":"answer","thumbnail":"https://pica.zhimg.com/80/v2-3c0fb8931f8f3a12093e12ac12dca3ac_720w.png"}]},{"type":"hot_list_feed","style_type":"1","id":"4_1658762809.6322527","card_id":"Q_544925093","target":{"id":544925093,"title":"两岁女童患尖锐湿疣，警方已介入调查，具体情况如何？儿童感染 HPV 的途径有哪些？","url":"https://api.zhihu.com/questions/544925093","type":"question","created":1658563521,"answer_count":136,"follower_count":485,"author":{"type":"people","user_type":"people","id":"0","url_token":"","url":"","name":"用户","headline":"","avatar_url":"https://pica.zhimg.com/aadd7b895_s.jpg"},"bound_topic_ids":[2146,12348,26526,128673,2141434],"comment_count":29,"is_following":false,"excerpt":"近日，两岁女童患尖锐湿疣一事引发网友的广泛关注。据@妇产科的陈大夫 表述，网友已联系到了关键人，确定了事发地，并已报警，警察和当地妇联都已跟进。对于2岁的女孩子来说，究竟是如何感染上的，父母难道没有一丁点察觉吗？http://news.hbtv.com.cn/p/2241163.html"},"attached_info":"Cj8Im4Pz3NOd09xaEAMaCDgzMzc3MTI2IMHX7pYGMB045QNABHIJNTQ0OTI1MDkzeACqAQliaWxsYm9hcmTSAQA=","detail_text":"781 万热度","trend":0,"debut":false,"children":[{"type":"answer","thumbnail":"https://pic1.zhimg.com/80/v2-dd5576066d22ad39dfde9699a4a0bb9a_1440w.png"}]},{"type":"hot_list_feed","style_type":"1","id":"5_1658762809.6329806","card_id":"Q_545251897","target":{"id":545251897,"title":"日媒称安倍晋三之妻所乘汽车遭警卫车追尾，如何看待这一事故？","url":"https://api.zhihu.com/questions/545251897","type":"question","created":1658741442,"answer_count":145,"follower_count":302,"author":{"type":"people","user_type":"people","id":"0","url_token":"","url":"","name":"用户","headline":"","avatar_url":"https://pica.zhimg.com/aadd7b895_s.jpg"},"bound_topic_ids":[229,400,38397,82131,105508],"comment_count":26,"is_following":false,"excerpt":"据日本朝日新闻、读卖新闻消息，当地时间7月25日，日本前首相安倍晋三的妻子昭惠女士所乘汽车在东京首都高速公路环线被一辆警卫车追尾。据悉，无人在事故中受伤，包括昭惠女士。（界面新闻）"},"attached_info":"Cj8Im4Pz3NOd09xaEAMaCDgzNDQ5OTA0IMLF+ZYGMBo4rgJABXIJNTQ1MjUxODk3eACqAQliaWxsYm9hcmTSAQA=","detail_text":"425 万热度","trend":0,"debut":false,"children":[{"type":"answer","thumbnail":"https://pic1.zhimg.com/80/v2-4a7daab77e99d748cb7c760fd8334e77_1440w.jpg?source=1940ef5c"}]},{"type":"hot_list_feed","style_type":"1","id":"6_1658762809.6335475","card_id":"Q_311433511","target":{"id":311433511,"title":"为什么几乎看不到跑车上高速？","url":"https://api.zhihu.com/questions/311433511","type":"question","created":1549521936,"answer_count":731,"follower_count":1917,"author":{"type":"people","user_type":"people","id":"0","url_token":"","url":"","name":"用户","headline":"","avatar_url":"https://pica.zhimg.com/aadd7b895_s.jpg"},"bound_topic_ids":[570,4055,9944,16143,19721],"comment_count":30,"is_following":false,"excerpt":"2019.9.12 补充 我就在高速公路公司工作过，跑车比例就是少。 别说我所在地方太穷，我在珠三角。 === 原提问： 驾龄16年，各汽车牌子基本认识吧，在市内夜店街、商场随处都能见到停放的跑车，但高速上几乎遇不到一次。（大商场长期有跑车停着） 想问问跑车车主们，是否极少用跑车跑长途，平时怎么玩跑车呢。 (注：这里的跑车也包含现代酷派等入门车，但不包括GOLF R/GTI、Focus RT这类“小钢炮”。高速上GTI还是挺常见的。) === 2019.2.13 更新 补充两点∶ 1、我家方圆1公里内5-6家夜店，牛马超跑也很少见，但保时捷挺多。 2、我常走的高速是跨省高速。以上两点可能也是造成“市区常见跑车，高速见不到跑车”的原因。"},"attached_info":"Cj8Im4Pz3NOd09xaEAMaCDMxNDgzOTA1IJCo7+IFMB44/Q5ABnIJMzExNDMzNTExeACqAQliaWxsYm9hcmTSAQA=","detail_text":"403 万热度","trend":0,"debut":false,"children":[{"type":"answer","thumbnail":"https://pic1.zhimg.com/50/v2-e81f6f0453ed392acaa3e5bd2c96c2d3_b.jpg"}]},{"type":"hot_list_feed","style_type":"1","id":"7_1658762809.63422","card_id":"Q_545174287","target":{"id":545174287,"title":"如何评价 Apple 官网产品降价？","url":"https://api.zhihu.com/questions/545174287","type":"question","created":1658719257,"answer_count":90,"follower_count":275,"author":{"type":"people","user_type":"people","id":"0","url_token":"","url":"","name":"用户","headline":"","avatar_url":"https://pica.zhimg.com/aadd7b895_s.jpg"},"bound_topic_ids":[366,487,520,3521],"comment_count":8,"is_following":false,"excerpt":"苹果官网显示，7月29 日至8月1日期间，部分商品可享150元～600元不等的优惠。 ​"},"attached_info":"Cj8Im4Pz3NOd09xaEAMaCDgzNDMyNTQxIJmY+JYGMAg4kwJAB3IJNTQ1MTc0Mjg3eACqAQliaWxsYm9hcmTSAQA=","detail_text":"390 万热度","trend":0,"debut":false,"children":[{"type":"answer","thumbnail":"https://pic4.zhimg.com/50/v2-026715f43441b90af90dc3306f2503ac_b.jpg"}]},{"type":"hot_list_feed","style_type":"1","id":"8_1658762809.6347427","card_id":"Q_545083473","target":{"id":545083473,"title":"今年蚊子明显感觉少了，是因为天气热的原因吗？","url":"https://api.zhihu.com/questions/545083473","type":"question","created":1658662476,"answer_count":103,"follower_count":255,"author":{"type":"people","user_type":"people","id":"0","url_token":"","url":"","name":"用户","headline":"","avatar_url":"https://pica.zhimg.com/aadd7b895_s.jpg"},"bound_topic_ids":[458,8438,2008294],"comment_count":12,"is_following":false,"excerpt":"不知道是不是我的错觉啊，今年的蚊子是不是少了啊…"},"attached_info":"Cj8Im4Pz3NOd09xaEAMaCDgzNDEyNDA0IMzc9JYGMAw4/wFACHIJNTQ1MDgzNDczeACqAQliaWxsYm9hcmTSAQA=","detail_text":"381 万热度","trend":0,"debut":false,"children":[{"type":"answer","thumbnail":"https://pic2.zhimg.com/80/v2-d451d5fa389f3eb443b5ae925434d8b8_1440w.png"}]},{"type":"hot_list_feed","style_type":"1","id":"9_1658762809.6352372","card_id":"Q_545263828","target":{"id":545263828,"title":"江西国控回应「网传一员工在朋友圈炫富秀权」，称「正在核实」，目前情况如何？","url":"https://api.zhihu.com/questions/545263828","type":"question","created":1658746740,"answer_count":113,"follower_count":296,"author":{"type":"people","user_type":"people","id":"0","url_token":"","url":"","name":"用户","headline":"","avatar_url":"https://pica.zhimg.com/aadd7b895_s.jpg"},"bound_topic_ids":[2566,5392,23428,24296,165829],"comment_count":10,"is_following":false,"excerpt":"近日，一组涉及“炫富”“秀后台”的朋友圈截图在网上引起广泛关注。截图显示，该名叫周劼的网友自称是江西省国有资本运营控股集团有限公司的员工。 7月25日下午，江西省国有资本运营控股集团有限公司一名工作人员告诉澎湃新闻（www.thepaper.cn），针对上述网传的信息，该公司正在调查、核实中。 澎湃新闻注意到，截至发稿，关于“周劼”的话题在微博阅读人数已达653.3万人次，讨论次数1.9万次。 网传图片显示，一个微信名为“周劼”的朋友圈发表了一些炫耀财富、家中有后台，互相帮忙走后门等言论，比如“父亲的副局长没问题了”“省厅人事处的人刚打了电话给我爸”，“感谢家族的所有人（三伯、大伯）”，炫耀一家人都有关系、有背景。 另外，此人多次提及党政机关干部，“和单位的一把手吃饭”“我办公室主任怕我吹空调冷，帮我加挡风板”“第一次进省长楼”等言论。 除此之外，上述“周劼”的朋友圈还有多次炫富言论，比如，声称自己喝的茶是“20万一斤的——2002年的白豪银针”；因戴欧米伽与苹果去省政府开会，被办公室处长点名开玩笑说要朴素一点，打算“换个华为跟跟风”。 澎湃新闻在江西省国有资本运营控股集团有限公司官网查询到，有一篇《公司副董事长、总经理阙泳一行赴进贤县进行调研》的通讯稿，官网显示作者名叫周劼，来源是行政办公室。 江西省国有资本运营控股集团有限公司官网显示，该公司成立于2004年5月，历经江西省外贸资产经营控股有限公司、江西省省属国有企业资产经营（控股）有限公司沿革，2022年3月更为现名。集团是经江西省人民政府批准设立、省国资委履行出资人职责并授权经营的国有资本运营平台。 江西国控回应“网传一员工在朋友圈炫富秀权”：正在核实"},"attached_info":"Cj8Im4Pz3NOd09xaEAMaCDgzNDUyNTcxIPTu+ZYGMAo4qAJACXIJNTQ1MjYzODI4eACqAQliaWxsYm9hcmTSAQA=","detail_text":"352 万热度","trend":0,"debut":true,"children":[{"type":"answer","thumbnail":"https://pic1.zhimg.com/v2-57479b816155f9dca1e5b2f7d1ea1d94_r.jpg?source=1940ef5c"}]},{"type":"hot_list_feed","style_type":"1","id":"10_1658762809.6360707","card_id":"Q_543958237","target":{"id":543958237,"title":"为什么犹太人在第二次世界大战期间不扮成其他族裔，以避免被处决呢？","url":"https://api.zhihu.com/questions/543958237","type":"question","created":1658129767,"answer_count":72,"follower_count":274,"author":{"type":"people","user_type":"people","id":"0","url_token":"","url":"","name":"用户","headline":"","avatar_url":"https://pica.zhimg.com/aadd7b895_s.jpg"},"bound_topic_ids":[8640,19593,2008294],"comment_count":14,"is_following":false,"excerpt":"在第二次世界大战期间，德国人对犹太人进行了惨无人道的屠杀。相信大家脑海当中肯定产生过疑问，那就是这些犹太人为何没有隐藏或者是伪装自己，以此来躲过灾祸。"},"attached_info":"Cj8Im4Pz3NOd09xaEAMaCDgzMTYyMjI5IOea1JYGMA44kgJACnIJNTQzOTU4MjM3eACqAQliaWxsYm9hcmTSAQA=","detail_text":"336 万热度","trend":0,"debut":false,"children":[{"type":"answer","thumbnail":"https://pic4.zhimg.com/50/v2-99d4012b941271342d2f32e47afc4f0d_b.jpg"}]},{"type":"hot_list_feed","style_type":"1","id":"11_1658762809.6368196","card_id":"Q_457776614","target":{"id":457776614,"title":"看过首映和点映的朋友们，沈腾、马丽主演的电影《独行月球》拍得怎么样？好看吗？","url":"https://api.zhihu.com/questions/457776614","type":"question","created":1620110870,"answer_count":215,"follower_count":527,"author":{"type":"people","user_type":"people","id":"0","url_token":"","url":"","name":"用户","headline":"","avatar_url":"https://pica.zhimg.com/aadd7b895_s.jpg"},"bound_topic_ids":[68,25509,66999,162005,687097],"comment_count":44,"is_following":false,"excerpt":"2022年上映"},"attached_info":"Cj8Im4Pz3NOd09xaEAMaCDY0MDA4MTUyIJbcw4QGMCw4jwRAC3IJNDU3Nzc2NjE0eACqAQliaWxsYm9hcmTSAQA=","detail_text":"305 万热度","trend":0,"debut":false,"children":[{"type":"answer","thumbnail":"https://pic2.zhimg.com/80/v2-dacd72858571c820eb045e8cd2404f67_1440w.jpg?source=1940ef5c"}]},{"type":"hot_list_feed","style_type":"1","id":"12_1658762809.6374004","card_id":"Q_544952026","target":{"id":544952026,"title":"如何看待 2022 上半年重庆 GDP 超越广州？","url":"https://api.zhihu.com/questions/544952026","type":"question","created":1658577412,"answer_count":253,"follower_count":520,"author":{"type":"people","user_type":"people","id":"0","url_token":"","url":"","name":"用户","headline":"","avatar_url":"https://pica.zhimg.com/aadd7b895_s.jpg"},"bound_topic_ids":[545,6331,17674,20052,45388],"comment_count":44,"is_following":false,"excerpt":"23日，广州市统计局通报，根据广东省地区生产总值统一核算结果，2022年上半年，广州市地区生产总值（GDP)为13433.80亿元，同比增长1.0%。其中，第一产业增加值为132.82亿元，同比增长2.4%；第二产业增加值为3763.30亿元，同比增长1.2%；第三产业增加值为9537.68亿元，同比增长0.9%。广州上半年GDP同比增长1.0% 6月份大多数行业生产经营活动企稳回升 重庆市统计局19日发布的2022年上半年重庆经济数据显示，上半年实现地区生产总值(GDP)13511.64亿元(人民币，下同)，同比增长4.0%。2022年上半年重庆GDP达1.35万亿元 同比增4.0%"},"attached_info":"Cj8Im4Pz3NOd09xaEAMaCDgzMzgzMTI5IITE75YGMCw4iARADHIJNTQ0OTUyMDI2eACqAQliaWxsYm9hcmTSAQA=","detail_text":"243 万热度","trend":0,"debut":false,"children":[{"type":"answer","thumbnail":"https://pic4.zhimg.com/80/v2-c348acf01ad7dcb85d5cdf6a3438f094_1440w.png"}]},{"type":"hot_list_feed","style_type":"1","id":"13_1658762809.6380894","card_id":"Q_277931415","target":{"id":277931415,"title":"老版《还珠格格》第一部里面演员为什么眼睛很亮，人物也很美，比现在的滤镜效果还要好？","url":"https://api.zhihu.com/questions/277931415","type":"question","created":1526808330,"answer_count":127,"follower_count":460,"author":{"type":"people","user_type":"people","id":"0","url_token":"","url":"","name":"用户","headline":"","avatar_url":"https://pica.zhimg.com/aadd7b895_s.jpg"},"bound_topic_ids":[2102,10479,23594,44844,140022],"comment_count":25,"is_following":false,"excerpt":""},"attached_info":"Cj8Im4Pz3NOd09xaEAMaCDI0MDM4MTM5IIr+hNgFMBk4zANADXIJMjc3OTMxNDE1eACqAQliaWxsYm9hcmTSAQA=","detail_text":"226 万热度","trend":0,"debut":false,"children":[{"type":"answer","thumbnail":"https://pica.zhimg.com/80/v2-5e137b333f5d349c6d8225b8c6bb364c_1440w.jpg?source=1940ef5c"}]},{"type":"hot_list_feed","style_type":"1","id":"14_1658762809.638554","card_id":"Q_544849126","target":{"id":544849126,"title":"如何看待「深圳一男子饭馆消费42元结账时付0.01元，说可以抵押电脑手机，但就是不给钱」？","url":"https://api.zhihu.com/questions/544849126","type":"question","created":1658534125,"answer_count":43,"follower_count":143,"author":{"type":"people","user_type":"people","id":"0","url_token":"","url":"","name":"用户","headline":"","avatar_url":"https://pica.zhimg.com/aadd7b895_s.jpg"},"bound_topic_ids":[215,404,31665,105508,2008294],"comment_count":6,"is_following":false,"excerpt":"男子消费42元结账时付0.01元#7月17日，广东深圳。一男子中午在黄女士店内就餐后未付钱，留下手机在店里充电后离开，下午再次来到店里吃饭后仍未付款。黄女士称，两顿饭共42元，多次提醒墙上有收款码后对方付了0.01元，且称可以抵押他的手机和电脑，自己老公表示就当免费请他吃顿饭，如果有困难可以理解，提前告知也可以免单，而不是这样欺骗。男子消费42元结账时付0.01元 店主：他说可以抵押电脑手机，但就是不给钱"},"attached_info":"Cj8Im4Pz3NOd09xaEAMaCDgzMzYwMzM0IO3x7JYGMAY4jwFADnIJNTQ0ODQ5MTI2eACqAQliaWxsYm9hcmTSAQA=","detail_text":"205 万热度","trend":0,"debut":false,"children":[{"type":"answer","thumbnail":"https://pic2.zhimg.com/80/v2-a87ffef6332002fdfdc0eb48ab14ec38_1440w.png"}]},{"type":"hot_list_feed","style_type":"1","id":"15_1658762809.6391478","card_id":"Q_544562717","target":{"id":544562717,"title":"《英雄联盟电竞经理》是不是快速收割粉丝经济的方式？","url":"https://api.zhihu.com/questions/544562717","type":"question","created":1658393605,"answer_count":90,"follower_count":130,"author":{"type":"people","user_type":"people","id":"0","url_token":"","url":"","name":"用户","headline":"","avatar_url":"https://pica.zhimg.com/aadd7b895_s.jpg"},"bound_topic_ids":[4392,18427,123302,1938502],"comment_count":5,"is_following":false,"excerpt":"昨天下载来玩，玩法挺简单的，重点还是战力。 满满的战力指数，感觉很适合收割饭圈，只能说谢谢饭圈让我们有比赛能看。"},"attached_info":"Cj8Im4Pz3NOd09xaEAMaCDgzMjk2NTAwIIWo5JYGMAU4ggFAD3IJNTQ0NTYyNzE3eACqAQliaWxsYm9hcmTSAQA=","detail_text":"168 万热度","trend":0,"debut":false,"children":[{"type":"answer","thumbnail":"https://pic2.zhimg.com/80/v2-62f0085212e8a4bfa4b022655d7c7355_1440w.jpg?source=1940ef5c"}]},{"type":"hot_list_feed","style_type":"1","id":"16_1658762809.6396663","card_id":"Q_544539933","target":{"id":544539933,"title":"江苏一外卖员因电梯误时殴打同乘业主，已被解雇。该外卖员可能承担哪些法律责任？","url":"https://api.zhihu.com/questions/544539933","type":"question","created":1658386076,"answer_count":108,"follower_count":213,"author":{"type":"people","user_type":"people","id":"0","url_token":"","url":"","name":"用户","headline":"","avatar_url":"https://pica.zhimg.com/aadd7b895_s.jpg"},"bound_topic_ids":[215,5582,11011,11422,25475],"comment_count":18,"is_following":false,"excerpt":"近日，江苏南通。据南通电视台报道，如东县掘港镇民生银河湾居民杨女士反映，在乘坐电梯时遇到一外卖员，他从15楼上了电梯准备回到1楼，由于杨女士在27楼按了电梯下行键，电梯就载着他上到了27楼，觉得电梯里耽误了他的时间，遂殴打杨女士。杨女士随后报警，目前，警方正在调查处理这件事。外卖员所属公司回应称，已经解雇该外卖员。https://app.myzaker.com/news/article.php?pk=62d8be2d8e9f09763236d4f3"},"attached_info":"Cj8Im4Pz3NOd09xaEAMaCDgzMjkxMzk0IJzt45YGMBI41QFAEHIJNTQ0NTM5OTMzeACqAQliaWxsYm9hcmTSAQA=","detail_text":"162 万热度","trend":0,"debut":false,"children":[{"type":"answer","thumbnail":"https://pic2.zhimg.com/80/v2-56e5121053647f25a7f22b5249cffa5d_1440w.png"}]},{"type":"hot_list_feed","style_type":"1","id":"17_1658762809.6402793","card_id":"Q_350742682","target":{"id":350742682,"title":"为什么骨传导耳机能保护听力，却还是很难冲击到目前的耳机市场格局呢？大家并不在意保护听力吗？","url":"https://api.zhihu.com/questions/350742682","type":"question","created":1571064735,"answer_count":134,"follower_count":331,"author":{"type":"people","user_type":"people","id":"0","url_token":"","url":"","name":"用户","headline":"","avatar_url":"https://pica.zhimg.com/aadd7b895_s.jpg"},"bound_topic_ids":[1367,7641,9262,113710,548154],"comment_count":10,"is_following":false,"excerpt":""},"attached_info":"Cj8Im4Pz3NOd09xaEAMaCDQwMjIwOTczIJ+Xku0FMAo4ywJAEXIJMzUwNzQyNjgyeACqAQliaWxsYm9hcmTSAQA=","detail_text":"149 万热度","trend":0,"debut":false,"children":[{"type":"answer","thumbnail":"https://pic4.zhimg.com/50/v2-4cc5b472a41b31a018146d68fa8a0383_b.jpg"}]},{"type":"hot_list_feed","style_type":"1","id":"18_1658762809.6406937","card_id":"Q_545147213","target":{"id":545147213,"title":"曾有 5 亿用户的飞信 App 将于 9 月 30 日停运，你对飞信有什么了解和印象？它为何会被取代？","url":"https://api.zhihu.com/questions/545147213","type":"question","created":1658712940,"answer_count":81,"follower_count":182,"author":{"type":"people","user_type":"people","id":"0","url_token":"","url":"","name":"用户","headline":"","avatar_url":"https://pica.zhimg.com/aadd7b895_s.jpg"},"bound_topic_ids":[99,2143,2154,2155,3555],"comment_count":11,"is_following":false,"excerpt":"中国移动近日发布公告，宣布调整和飞信业务，自9月30日开始停止提供该服务，这意味着曾经收获5亿注册用户的飞信APP将正式走下历史舞台。中国移动宣布飞信app停运"},"attached_info":"Cj8Im4Pz3NOd09xaEAMaCDgzNDI2NDk2IOzm95YGMAs4tgFAEnIJNTQ1MTQ3MjEzeACqAQliaWxsYm9hcmTSAQA=","detail_text":"137 万热度","trend":0,"debut":false,"children":[{"type":"answer","thumbnail":"https://pic4.zhimg.com/80/v2-33e8e34f96795c064039e07892a2b301_1440w.png"}]},{"type":"hot_list_feed","style_type":"1","id":"19_1658762809.641318","card_id":"Q_545215785","target":{"id":545215785,"title":"电车 80 度电最多能跑多少公里？","url":"https://api.zhihu.com/questions/545215785","type":"question","created":1658731158,"answer_count":25,"follower_count":56,"author":{"type":"people","user_type":"people","id":"0","url_token":"","url":"","name":"用户","headline":"","avatar_url":"https://pica.zhimg.com/aadd7b895_s.jpg"},"bound_topic_ids":[570,1842,9595,60628,126578],"comment_count":0,"is_following":false,"excerpt":"在 2022 年的当下，电动汽车的电池能量密度和整车技术都相比于前几年有了突飞猛进的发展，不同的品牌在使用相同的电池容量的时候也会出现不同的续航里程表现，这跟整车制造工艺、系统效率等等密切相关，想知道在目前技术条件下，电动汽车 80 度电，一般能跑多少公里？行业内比较优秀水平的电动汽车能跑多少公里？行业天花板又是多少？"},"attached_info":"Cj4Im4Pz3NOd09xaEAMaCDgzNDQxODQ4IJb1+JYGMAA4OEATcgk1NDUyMTU3ODV4AKoBCWJpbGxib2FyZNIBAA==","detail_text":"127 万热度","trend":0,"debut":true,"children":[{"type":"answer","thumbnail":"https://pic3.zhimg.com/50/v2-13b1b44c051af8f46d438d0b80086335_b.jpg"}]},{"type":"hot_list_feed","style_type":"1","id":"20_1658762809.641763","card_id":"Q_543758885","target":{"id":543758885,"title":"如何看待安卓主摄像素从 1亿 回落到现在的 5000 万，原因是什么？","url":"https://api.zhihu.com/questions/543758885","type":"question","created":1658030724,"answer_count":32,"follower_count":77,"author":{"type":"people","user_type":"people","id":"0","url_token":"","url":"","name":"用户","headline":"","avatar_url":"https://pica.zhimg.com/aadd7b895_s.jpg"},"bound_topic_ids":[488,2042,4768,5291,104165],"comment_count":1,"is_following":false,"excerpt":""},"attached_info":"Cj4Im4Pz3NOd09xaEAMaCDgzMTE3OTEzIISVzpYGMAE4TUAUcgk1NDM3NTg4ODV4AKoBCWJpbGxib2FyZNIBAA==","detail_text":"124 万热度","trend":0,"debut":false,"children":[{"type":"answer","thumbnail":"https://pic2.zhimg.com/50/v2-8f2753f9692cd29baa9f777876748182_b.jpg"}]},{"type":"hot_list_feed","style_type":"1","id":"21_1658762809.6421883","card_id":"Q_545058711","target":{"id":545058711,"title":"特朗普称拜登把美国从最强大国家变成弱国，满世界讨能源，如何评价这一言论？","url":"https://api.zhihu.com/questions/545058711","type":"question","created":1658649588,"answer_count":144,"follower_count":467,"author":{"type":"people","user_type":"people","id":"0","url_token":"","url":"","name":"用户","headline":"","avatar_url":"https://pica.zhimg.com/aadd7b895_s.jpg"},"bound_topic_ids":[2161,3853,4621,100510,159978],"comment_count":26,"is_following":false,"excerpt":"据俄罗斯《消息报》24日报道，美国前总统特朗普在佛罗里达州出席高校学生活动时表示，拜登把美利坚合众国变成了穷国。 特朗普说：“现在我们是个穷国。拥有满世界讨能源、寻求帮助的下跪的拜登（总统）的穷国。” 报道称，特朗普还说，两年前美国还是强国，在解决能源依赖问题上已接近于“比沙特加俄罗斯（的产量）还要大”。 他说：“仅用了两年时间，在得到世界认可和尊重方面，我们就从最强大的国家…变成了弱（国）。没人再尊重我们。” （参考消息网）"},"attached_info":"Cj8Im4Pz3NOd09xaEAMaCDgzNDA2OTAzIPT385YGMBo40wNAFXIJNTQ1MDU4NzExeACqAQliaWxsYm9hcmTSAQA=","detail_text":"116 万热度","trend":0,"debut":false,"children":[{"type":"answer","thumbnail":"https://pic4.zhimg.com/v2-19e6c8e457d5a72ccf67a45cce203d4b_1440w.jpg?source=172ae18b"}]},{"type":"hot_list_feed","style_type":"1","id":"22_1658762809.6427715","card_id":"Q_545260792","target":{"id":545260792,"title":"7 月 25 日郑州黑云压城、暴雨突至电闪雷鸣，你那里情况如何？需要哪些预防措施？","url":"https://api.zhihu.com/questions/545260792","type":"question","created":1658745238,"answer_count":67,"follower_count":98,"author":{"type":"people","user_type":"people","id":"0","url_token":"","url":"","name":"用户","headline":"","avatar_url":"https://pica.zhimg.com/aadd7b895_s.jpg"},"bound_topic_ids":[22845,100973,729899,1328222,1341981],"comment_count":4,"is_following":false,"excerpt":"大河网讯 7月25日17时45分，郑州气象台发布雷暴大风黄色预警信号：预计未来6小时内，郑州市主城区、上街区、航空港区将受雷暴大风天气影响，阵风风力7级以上，局地9级以上，并伴有强雷电、短时强降水、冰雹。请注意防范强对流天气带来的不利影响。 大河网提醒广大民众:请注意关好门窗，以免雨水进入户内浸湿地板或家具；雷雨时尽量不使用室内热水器、电视机、电脑等电器，并拔除电源插头；车辆请谨慎慢行，以免因视线不清、路面打滑失控。（范昭 牧堃 杨鑫阳 马绍坤 李思 豫刘晓明 实习生 魏凯）【大河网景】黑云压城暴雨来！郑州发布雷暴大风黄色预警"},"attached_info":"Cj4Im4Pz3NOd09xaEAMaCDgzNDUxOTAxIJbj+ZYGMAQ4YkAWcgk1NDUyNjA3OTJ4AKoBCWJpbGxib2FyZNIBAA==","detail_text":"108 万热度","trend":0,"debut":false,"children":[{"type":"answer","thumbnail":"https://pic1.zhimg.com/50/v2-0f553d7d949368873929aea267513460_b.jpg"}]},{"type":"hot_list_feed","style_type":"1","id":"23_1658762809.643366","card_id":"Q_545207740","target":{"id":545207740,"title":"中国空间站问天试验舱部署四个实验柜，其中那个外观奇特的柜子是做什么用的？有哪些研究成果值得期待？","url":"https://api.zhihu.com/questions/545207740","type":"question","created":1658729350,"answer_count":25,"follower_count":56,"author":{"type":"people","user_type":"people","id":"0","url_token":"","url":"","name":"用户","headline":"","avatar_url":"https://pica.zhimg.com/aadd7b895_s.jpg"},"bound_topic_ids":[3087,4913,24600,153160,1937094],"comment_count":6,"is_following":false,"excerpt":"7月24日14时22分，搭载问天实验舱的长征五号B遥三运载火箭，在我国文昌航天发射场准时点火发射，约495秒后，问天实验舱与火箭成功分离并进入预定轨道，发射取得圆满成功。 作为中国空间站首个科学实验舱，“问天”未来将开展哪些实验？中国载人航天工程空间应用系统副总师、中科院空间应用中心研究员吕从民介绍，空间应用系统问天实验舱任务以生命科学和生物技术研究为主，在空间生命科学与生物技术、微重力流体物理、空间材料科学、空间应用新技术试验等四个领域规划部署了十余个研究主题，空间站建成后将持续论证、滚动实施相关科学项目。 据他介绍，为保证科学任务顺利开展，不断产出科学成果，空间应用系统在问天实验舱部署了生命生态实验柜、生物技术实验柜、科学手套箱与低温存储柜、变重力科学实验柜等科学实验设施，配置了舱内外应用任务共用支持设备，联合支持科学项目在轨全任务链实施。 其中一个外观奇特的柜子引起了网友的好奇，这个实验柜究竟是做什么用的？"},"attached_info":"Cj4Im4Pz3NOd09xaEAMaCDgzNDQwMDQyIIbn+JYGMAY4OEAXcgk1NDUyMDc3NDB4AKoBCWJpbGxib2FyZNIBAA==","detail_text":"105 万热度","trend":0,"debut":true,"children":[{"type":"answer","thumbnail":"https://pic4.zhimg.com/50/v2-28c75b0da67e39d73505581ba8fa827b_b.jpg"}]},{"type":"hot_list_feed","style_type":"1","id":"24_1658762809.6440277","card_id":"Q_544670094","target":{"id":544670094,"title":"小米造车迎来新进展，曝五菱营销高管周钘下个月加盟小米，这对公司业务发展有何助力？","url":"https://api.zhihu.com/questions/544670094","type":"question","created":1658450057,"answer_count":30,"follower_count":101,"author":{"type":"people","user_type":"people","id":"0","url_token":"","url":"","name":"用户","headline":"","avatar_url":"https://pica.zhimg.com/aadd7b895_s.jpg"},"bound_topic_ids":[890,25405,60628,719320,1062620],"comment_count":6,"is_following":false,"excerpt":"IT之家7 月 22 日消息，小米在去年 3 月底官宣造车，并在去年 9 月注册成立了小米汽车有限公司，负责智能电动汽车业务。小米表示，首期投资为 100 亿元人民币，预计未来 10 年投资约 600 亿元，雷军将兼任智能电动汽车业务的首席执行官。 自从那时以来，小米造车便备受网友关注。时隔半年，小米造车又有了新的进展。 多个媒体报道称，原上汽通用五菱销售公司副总经理周钘将于 8 月正式加入小米汽车，担任小米汽车营销方面负责人，直接向小米科技董事长雷军汇报。这一消息得到了周钘本人的确认，但对方并未透露更多信息。而上汽通用五菱相关负责人表示周钘已确认将离职：“周钘先生的职业规划属于他个人空间，我们不便做更多探讨，祝福周钘先生后续工作生活一切顺利。” 业内人士分析认为，周钘加盟小米汽车，意味着小米汽车进展顺利，已开始着手在销售端进行布局。 IT之家了解到，周钘于 2011 年加入上汽通用五菱，在多个关键岗位任职。2018 年周钘的公开身份为上汽通用五菱销售公司的营销中心总监。随后，由于业绩突出，周钘又升任为上汽通用五菱销售公司副总经理。"},"attached_info":"Cj4Im4Pz3NOd09xaEAMaCDgzMzIwNTA1IInh55YGMAY4ZUAYcgk1NDQ2NzAwOTR4AKoBCWJpbGxib2FyZNIBAA==","detail_text":"102 万热度","trend":0,"debut":true,"children":[{"type":"answer","thumbnail":"https://pic1.zhimg.com/80/v2-f511896a6dd78e295b589974798ab6dc_1440w.jpg?source=1940ef5c"}]},{"type":"hot_list_feed","style_type":"1","id":"25_1658762809.6448262","card_id":"Q_544771645","target":{"id":544771645,"title":"数学专业领域的人看《天才基本法》是什么感受？","url":"https://api.zhihu.com/questions/544771645","type":"question","created":1658482948,"answer_count":47,"follower_count":265,"author":{"type":"people","user_type":"people","id":"0","url_token":"","url":"","name":"用户","headline":"","avatar_url":"https://pica.zhimg.com/aadd7b895_s.jpg"},"bound_topic_ids":[2102,44913,156805,599623,2093583],"comment_count":4,"is_following":false,"excerpt":""},"attached_info":"Cj8Im4Pz3NOd09xaEAMaCDgzMzQzMDkyIITi6ZYGMAQ4iQJAGXIJNTQ0NzcxNjQ1eACqAQliaWxsYm9hcmTSAQA=","detail_text":"59 万热度","trend":0,"debut":false,"children":[{"type":"answer","thumbnail":"https://pic3.zhimg.com/50/v2-af0a7222816e782cd9abbc3d6ecb48f1_b.jpg"}]},{"type":"hot_list_feed","style_type":"1","id":"26_1658762809.645193","card_id":"Q_544943029","target":{"id":544943029,"title":"美国援乌F-16战机正式提上日程，无辜的俄军士兵该何去何从？","url":"https://api.zhihu.com/questions/544943029","type":"question","created":1658571784,"answer_count":119,"follower_count":153,"author":{"type":"people","user_type":"people","id":"0","url_token":"","url":"","name":"用户","headline":"","avatar_url":"https://pica.zhimg.com/aadd7b895_s.jpg"},"bound_topic_ids":[472,5548,63570,136525,1973765],"comment_count":18,"is_following":false,"excerpt":"美国援乌F-16战机计划启动！ 在乌克兰境内，已经失去空中力量的俄军，将何去何从？"},"attached_info":"Cj8Im4Pz3NOd09xaEAMaCDgzMzgxMTA5IIiY75YGMBI4mQFAGnIJNTQ0OTQzMDI5eACqAQliaWxsYm9hcmTSAQA=","detail_text":"59 万热度","trend":0,"debut":false,"children":[{"type":"answer","thumbnail":""}]},{"type":"hot_list_feed","style_type":"1","id":"27_1658762809.645657","card_id":"Q_545151612","target":{"id":545151612,"title":"接待吴啊萍供奉的僧人灵松初中辍学，曾因交通肇事获刑，如何看待此事？这一岗位的僧人应具备哪些素质和能力？","url":"https://api.zhihu.com/questions/545151612","type":"question","created":1658714098,"answer_count":216,"follower_count":452,"author":{"type":"people","user_type":"people","id":"0","url_token":"","url":"","name":"用户","headline":"","avatar_url":"https://pica.zhimg.com/aadd7b895_s.jpg"},"bound_topic_ids":[2281,5582,6860,111829,2138950],"comment_count":22,"is_following":false,"excerpt":"7月24日晚，南京发布《关于南京玄奘寺供奉侵华日军战犯牌位事件调查处理情况的通报》，其中提到2017年接待吴啊萍供奉的当值僧人为灵松（1979年9月生，初中辍学）。 记者注意到，在南京玄奘寺的社交账号中，曾多次提及灵松，其经常以玄奘寺代表的身份出席社会活动，在寺内则负责为他人供灯祈福等业务；已被撤换的住持传真还撰文称灵松为其徒弟，并提到灵松曾未经住持同意，私自驾驶寺庙车辆外出，交通肇事驾车撞死人后获刑2年。 据悉，南京市有关部门正对玄奘寺及相关人员其他问题线索，依法依规作进一步调查处理。接待吴啊萍供奉的僧人灵松，系玄奘寺住持传真徒弟，初中辍学，曾因交通肇事获刑"},"attached_info":"Cj8Im4Pz3NOd09xaEAMaCDgzNDI3NDkyIPLv95YGMBY4xANAG3IJNTQ1MTUxNjEyeACqAQliaWxsYm9hcmTSAQA=","detail_text":"55 万热度","trend":0,"debut":false,"children":[{"type":"answer","thumbnail":"https://pic2.zhimg.com/80/v2-7b07b935a7d2caae3e51179742115bb6_1440w.png"}]},{"type":"hot_list_feed","style_type":"1","id":"28_1658762809.64627","card_id":"Q_545225979","target":{"id":545225979,"title":"邢台学院被曝出疑似存在批量引进「速成博士」，这批博士此前或为邢台学院在职教师，还有哪些信息值得关注？","url":"https://api.zhihu.com/questions/545225979","type":"question","created":1658733668,"answer_count":36,"follower_count":127,"author":{"type":"people","user_type":"people","id":"0","url_token":"","url":"","name":"用户","headline":"","avatar_url":"https://pica.zhimg.com/aadd7b895_s.jpg"},"bound_topic_ids":[5259,6794,105508,171020,405338],"comment_count":4,"is_following":false,"excerpt":"邢台学院也被曝出疑似存在批量引进“速成博士”的情况。据了解，今年2月邢台学院公布了一份2021年公开选聘拟聘人员名单，共13人，均为韩国高校博士，有网友根据名单发现，这批博士此前或为邢台学院在职教师。针对爆料，新黄河记者检索邢台学院官网以及邢台市人力资源和社会保障局官网，证实了该校引进13名韩国博士这一消息，但关于13位博士的详细资料，该校官网并没有公布。 针对网友的质疑，记者多次致电邢台学院各科室，工作人员均称并不了解相关情况。随后记者根据邢台学院选聘名单公示中的监督电话，联系到邢台市教育局，工作人员称，此事需要核实由哪个科室负责，随后再作回复。截至记者发稿，暂未得到相关回复。又一起！邢台学院被曝引进韩国博士，起底“速成博士”产业链"},"attached_info":"Cj4Im4Pz3NOd09xaEAMaCDgzNDQ0MTE5IOSI+ZYGMAQ4f0Accgk1NDUyMjU5Nzl4AKoBCWJpbGxib2FyZNIBAA==","detail_text":"54 万热度","trend":0,"debut":false,"children":[{"type":"answer","thumbnail":"https://pic4.zhimg.com/80/v2-8f85344789572fec34dfe699822a8cb8_1440w.png"}]},{"type":"hot_list_feed","style_type":"1","id":"29_1658762809.6469302","card_id":"Q_543261227","target":{"id":543261227,"title":"如何看待 AMD 7950X 被 Intel i9 13900K 吊打？","url":"https://api.zhihu.com/questions/543261227","type":"question","created":1657784014,"answer_count":46,"follower_count":85,"author":{"type":"people","user_type":"people","id":"0","url_token":"","url":"","name":"用户","headline":"","avatar_url":"https://pica.zhimg.com/aadd7b895_s.jpg"},"bound_topic_ids":[847,4172,4206,5263],"comment_count":4,"is_following":false,"excerpt":""},"attached_info":"Cj4Im4Pz3NOd09xaEAMaCDgzMDA3MDAzIM6Nv5YGMAQ4VUAdcgk1NDMyNjEyMjd4AKoBCWJpbGxib2FyZNIBAA==","detail_text":"47 万热度","trend":0,"debut":false,"children":[{"type":"answer","thumbnail":"https://pic4.zhimg.com/50/v2-a1b84512570ada0c0fe4b3db090a8923_b.jpg"}]},{"type":"hot_list_feed","style_type":"1","id":"30_1658762809.6473372","card_id":"Q_544504238","target":{"id":544504238,"title":"华中农大研究发现塑料颗粒进入孕鼠胎儿脑内，影响其神经发育。塑料污染会对人类产生相似影响吗？","url":"https://api.zhihu.com/questions/544504238","type":"question","created":1658371768,"answer_count":27,"follower_count":93,"author":{"type":"people","user_type":"people","id":"0","url_token":"","url":"","name":"用户","headline":"","avatar_url":"https://pica.zhimg.com/aadd7b895_s.jpg"},"bound_topic_ids":[237,21045,22624,40543,224305],"comment_count":1,"is_following":false,"excerpt":"研究发现：塑料降解颗粒或为精神疾病潜在发病原因"},"attached_info":"Cj4Im4Pz3NOd09xaEAMaCDgzMjgzMzY2ILj94pYGMAE4XUAecgk1NDQ1MDQyMzh4AKoBCWJpbGxib2FyZNIBAA==","detail_text":"41 万热度","trend":0,"debut":false,"children":[{"type":"answer","thumbnail":"https://pic1.zhimg.com/80/v2-30aaa710638555e9d04481349f3983b8_1440w.jpg?source=1940ef5c"}]},{"type":"hot_list_feed","style_type":"1","id":"31_1658762809.6478696","card_id":"Q_545091228","target":{"id":545091228,"title":"如何评价《极限挑战》第八季第五期？","url":"https://api.zhihu.com/questions/545091228","type":"question","created":1658666914,"answer_count":48,"follower_count":54,"author":{"type":"people","user_type":"people","id":"0","url_token":"","url":"","name":"用户","headline":"","avatar_url":"https://pica.zhimg.com/aadd7b895_s.jpg"},"bound_topic_ids":[11334,22839,1391411,2065275,2093583],"comment_count":1,"is_following":false,"excerpt":""},"attached_info":"Cj4Im4Pz3NOd09xaEAMaCDgzNDE0MTA0IKL/9JYGMAE4NkAfcgk1NDUwOTEyMjh4AKoBCWJpbGxib2FyZNIBAA==","detail_text":"41 万热度","trend":0,"debut":false,"children":[{"type":"answer","thumbnail":"https://pica.zhimg.com/80/v2-f31ac41f82224b496ce65d658b2bf607_720w.png"}]},{"type":"hot_list_feed","style_type":"1","id":"32_1658762809.6483376","card_id":"Q_545173625","target":{"id":545173625,"title":"读大学了，买二手手机可怜吗?","url":"https://api.zhihu.com/questions/545173625","type":"question","created":1658719108,"answer_count":213,"follower_count":217,"author":{"type":"people","user_type":"people","id":"0","url_token":"","url":"","name":"用户","headline":"","avatar_url":"https://pica.zhimg.com/aadd7b895_s.jpg"},"bound_topic_ids":[676,6972,18211,1382716,2035860],"comment_count":21,"is_following":false,"excerpt":"我是一个准大学生，之前用的手机基本是二手机，心里一直有个新手机的梦想，准备读大学了，想买一台好一点的手机，心里是很想要新手机的，但是感觉二手机会划算很多，但是又感觉考上大学了，还只能用二手机觉得很可怜也没必要。所以，为了一千块钱买二手机可怜吗？"},"attached_info":"Cj8Im4Pz3NOd09xaEAMaCDgzNDMyMzk4IISX+JYGMBU42QFAIHIJNTQ1MTczNjI1eACqAQliaWxsYm9hcmTSAQA=","detail_text":"41 万热度","trend":0,"debut":false,"children":[{"type":"answer","thumbnail":"https://pic2.zhimg.com/80/v2-b5ded970fd7c290ab9558060aab68de8_1440w.png"}]},{"type":"hot_list_feed","style_type":"1","id":"33_1658762809.6488938","card_id":"Q_544659689","target":{"id":544659689,"title":"如果被《咒》里面的大黑佛母缠上了，该怎么自救？","url":"https://api.zhihu.com/questions/544659689","type":"question","created":1658427509,"answer_count":315,"follower_count":382,"author":{"type":"people","user_type":"people","id":"0","url_token":"","url":"","name":"用户","headline":"","avatar_url":"https://pica.zhimg.com/aadd7b895_s.jpg"},"bound_topic_ids":[6860,8049,18833,761502,2117400],"comment_count":32,"is_following":false,"excerpt":"如果真的被大黑佛母缠上了，该怎么办？ 有没有物理方法或者精神方法进行对抗的？ 最好有比较简单易行，成本不高，而且不会社死的方法。"},"attached_info":"Cj8Im4Pz3NOd09xaEAMaCDgzMzE4MTUzIPWw5pYGMCA4/gJAIXIJNTQ0NjU5Njg5eACqAQliaWxsYm9hcmTSAQA=","detail_text":"41 万热度","trend":0,"debut":false,"children":[{"type":"answer","thumbnail":"https://pic1.zhimg.com/80/v2-d7a8fa67ad62bdf6563f94dfc3e5b706_1440w.jpg?source=1940ef5c"}]},{"type":"hot_list_feed","style_type":"1","id":"34_1658762809.6493895","card_id":"Q_544769578","target":{"id":544769578,"title":"读不懂一些文学作品，不懂它们要表达什么，是我知识太少，理解能力不够，还是时代不同，我和书有代沟？","url":"https://api.zhihu.com/questions/544769578","type":"question","created":1658482177,"answer_count":42,"follower_count":102,"author":{"type":"people","user_type":"people","id":"0","url_token":"","url":"","name":"用户","headline":"","avatar_url":"https://pica.zhimg.com/aadd7b895_s.jpg"},"bound_topic_ids":[4363,16863,157162],"comment_count":4,"is_following":false,"excerpt":"最近看的书真的是一点都不懂。重新看了一遍老人与海，看完之后回想了一下学校老师的解读，觉得怪怪的，不懂。看霍乱时期的爱情，局外人，百年孤独，月亮与六便士。还有洛丽塔，这些名著，我看不懂，我不知道我可不可以用我的三观去评价，衡量。尤其是洛丽塔，嗯.,...作者到底要表达什么，体现什么呢。还是说文学小说本就是一个个，故事，不需要有所体现呢？ 还有很多日本文学，《伊豆舞女》《失乐园》之类的很有名的书，看了我有点不舒服。渡边淳一的书我最不喜欢。村上春树的书我也看不懂。感觉像是在看他的日记。《人间失格》等私小说看着觉得新奇，看的时候也会为书中的人流泪，但多加了解一下作者（比如太宰治），就又不是那么喜欢看私小说了。我对这类书的感觉就是“挺有意思的故事书”。 中国作家的书，最近看的有余华和莫言和三毛的书。这三个人的书我都挺喜欢的，但我不懂莫言书中的语言那么的...嗯...不知道怎么形容，可能是我看的书太少了，他的语言很直接，很形象，很有他个人特色，看了他的丰乳肥臀和生死疲劳。生死疲劳我很喜欢，看完之后呆了很久，我3，4天，也算是一口气看完的吧？看完之后呆了很久，给我很大震撼，到底是一个什么样的人才能写出这样的文字？我惊叹于他的想象力与他的文笔。但看不太懂丰乳肥臀，故事是懂了写的什么，但不知道他想表达什么。之前看的国内的小说也常有这样的感觉。故事我是懂了，但作者想表达什么呢？不懂。"},"attached_info":"Cj4Im4Pz3NOd09xaEAMaCDgzMzQyNjMyIIHc6ZYGMAQ4ZkAicgk1NDQ3Njk1Nzh4AKoBCWJpbGxib2FyZNIBAA==","detail_text":"40 万热度","trend":0,"debut":false,"children":[{"type":"answer","thumbnail":"https://pic3.zhimg.com/50/v2-5bcb63377ee26e653a4c8cc960ac4240_b.jpg"}]},{"type":"hot_list_feed","style_type":"1","id":"35_1658762809.6504462","card_id":"Q_544613555","target":{"id":544613555,"title":"送去修电脑会被换零件吗？","url":"https://api.zhihu.com/questions/544613555","type":"question","created":1658415154,"answer_count":50,"follower_count":66,"author":{"type":"people","user_type":"people","id":"0","url_token":"","url":"","name":"用户","headline":"","avatar_url":"https://pica.zhimg.com/aadd7b895_s.jpg"},"bound_topic_ids":[23,3132,10222,87688,154649],"comment_count":9,"is_following":false,"excerpt":"我家是13年买的电脑，因为家里人都不太会玩电脑，后来不小心下了流氓软件，导致电脑特别卡。因为家里没人会整，所以送去电脑店清了一下，中间有将近两个多小时不在，去上课了，然后后来又有将近一个小时不在。电脑刚拿回家确实干净了很多，然后我就打算从新下点软件，用师傅给下的360下的。拿电脑的时候师傅就说以后下东西用360就行。洗个澡回来发现电脑卡了，时间一直定格在洗澡前的时间。 这两天又从新开机试了一下，发现根本打不开，都是黑屏，然后屏幕上又那个转圈圈加载的东西转了一圈也卡住不到了。要不就是提示我Windows似乎未正确加载。 我爸听我要修电脑，就和我妈说别让人把电脑零件换了。我说13年的老电脑了，又不是什么名牌，也不是多好的型号，不至于。 那个店主还挺好说话，看我们在那里站着等还特意搬东西让我们坐，最后修的时间长还说实在不行让我们先回去，一会修完他们给送过来。 然后我妈也稍微放了点心。结果今天打开看还是打不开，她就急了，一直叹气，摔东西，话里话外怪我把电脑拿去修。 我最近上网课，用手机看很费眼睛，就想着去修修电脑，用电脑看。我爸我妈小学没毕业，也不会整电脑，我也不会整电脑，这种情况也只能去找人修了啊。我还怕被骗，找了我同学买电脑的那家店去的。 我真不理解。是我的错吗？所有修电脑的都会换零件吗？"},"attached_info":"Cj4Im4Pz3NOd09xaEAMaCDgzMzA3ODM4ILLQ5ZYGMAk4QkAjcgk1NDQ2MTM1NTV4AKoBCWJpbGxib2FyZNIBAA==","detail_text":"40 万热度","trend":0,"debut":false,"children":[{"type":"answer","thumbnail":""}]},{"type":"hot_list_feed","style_type":"1","id":"36_1658762809.6511052","card_id":"Q_545101927","target":{"id":545101927,"title":"自己考了一个公办的大专，父母不高兴不太想让我读觉得浪费钱，要继续读吗？","url":"https://api.zhihu.com/questions/545101927","type":"question","created":1658671779,"answer_count":91,"follower_count":99,"author":{"type":"people","user_type":"people","id":"0","url_token":"","url":"","name":"用户","headline":"","avatar_url":"https://pica.zhimg.com/aadd7b895_s.jpg"},"bound_topic_ids":[35316,47496,74149],"comment_count":2,"is_following":false,"excerpt":"爸妈不太想给我学费让我自己打工赚钱，可是我找不到暑假工，家人们怎么办我要去读嘛？"},"attached_info":"Cj4Im4Pz3NOd09xaEAMaCDgzNDE2NDU2IKOl9ZYGMAI4Y0Akcgk1NDUxMDE5Mjd4AKoBCWJpbGxib2FyZNIBAA==","detail_text":"40 万热度","trend":0,"debut":false,"children":[{"type":"answer","thumbnail":""}]},{"type":"hot_list_feed","style_type":"1","id":"37_1658762809.6514738","card_id":"Q_544869784","target":{"id":544869784,"title":"高中三年要有多努力才能在普通中学考上一本?","url":"https://api.zhihu.com/questions/544869784","type":"question","created":1658542056,"answer_count":127,"follower_count":158,"author":{"type":"people","user_type":"people","id":"0","url_token":"","url":"","name":"用户","headline":"","avatar_url":"https://pica.zhimg.com/aadd7b895_s.jpg"},"bound_topic_ids":[4570,6659,41299],"comment_count":9,"is_following":false,"excerpt":"我中考失利，本来是能上重点高中的，结果只上了普通高中，想问问各位，高中三年要有多努力才能在普通高中脱颖而出，是不是拒绝手机和一切外界事物，另外高一就开始尝试做一些高考卷可行吗？希望各位大神指教"},"attached_info":"Cj8Im4Pz3NOd09xaEAMaCDgzMzY0ODYyIOiv7ZYGMAk4ngFAJXIJNTQ0ODY5Nzg0eACqAQliaWxsYm9hcmTSAQA=","detail_text":"40 万热度","trend":0,"debut":false,"children":[{"type":"answer","thumbnail":""}]},{"type":"hot_list_feed","style_type":"1","id":"38_1658762809.6518488","card_id":"Q_545155849","target":{"id":545155849,"title":"如何评价时代少年团新歌《绝配》？","url":"https://api.zhihu.com/questions/545155849","type":"question","created":1658715074,"answer_count":57,"follower_count":51,"author":{"type":"people","user_type":"people","id":"0","url_token":"","url":"","name":"用户","headline":"","avatar_url":"https://pica.zhimg.com/aadd7b895_s.jpg"},"bound_topic_ids":[3662,77417,114119,465064],"comment_count":0,"is_following":false,"excerpt":""},"attached_info":"Cj4Im4Pz3NOd09xaEAMaCDgzNDI4NDQ0IML395YGMAA4M0Amcgk1NDUxNTU4NDl4AKoBCWJpbGxib2FyZNIBAA==","detail_text":"40 万热度","trend":0,"debut":false,"children":[{"type":"answer","thumbnail":""}]},{"type":"hot_list_feed","style_type":"1","id":"39_1658762809.6521728","card_id":"Q_338672106","target":{"id":338672106,"title":"《甄嬛传》中崔槿汐和苏培盛对食一事败露被抓进慎刑司之后，皇帝为什么不主动去救苏培盛？","url":"https://api.zhihu.com/questions/338672106","type":"question","created":1564916308,"answer_count":33,"follower_count":75,"author":{"type":"people","user_type":"people","id":"0","url_token":"","url":"","name":"用户","headline":"","avatar_url":"https://pica.zhimg.com/aadd7b895_s.jpg"},"bound_topic_ids":[53690,76577,144837,2012788,2012789],"comment_count":1,"is_following":false,"excerpt":""},"attached_info":"Cj4Im4Pz3NOd09xaEAMaCDM3NTM3MjA4INT0muoFMAE4S0AncgkzMzg2NzIxMDZ4AKoBCWJpbGxib2FyZNIBAA==","detail_text":"40 万热度","trend":0,"debut":false,"children":[{"type":"answer","thumbnail":"https://picx.zhimg.com/80/v2-38a96043b09d084b24840cf7c6c3f78c_1440w.jpg?source=1940ef5c"}]},{"type":"hot_list_feed","style_type":"1","id":"40_1658762809.652668","card_id":"Q_544062456","target":{"id":544062456,"title":"如何看待中山大学 2022 年广东物理类录取最低排位跌至 13023 名？","url":"https://api.zhihu.com/questions/544062456","type":"question","created":1658189023,"answer_count":36,"follower_count":114,"author":{"type":"people","user_type":"people","id":"0","url_token":"","url":"","name":"用户","headline":"","avatar_url":"https://pica.zhimg.com/aadd7b895_s.jpg"},"bound_topic_ids":[2403,18597,19509,20290,582774],"comment_count":2,"is_following":false,"excerpt":""},"attached_info":"Cj4Im4Pz3NOd09xaEAMaCDgzMTg1Mzk4IN/p15YGMAI4ckAocgk1NDQwNjI0NTZ4AKoBCWJpbGxib2FyZNIBAA==","detail_text":"40 万热度","trend":0,"debut":false,"children":[{"type":"answer","thumbnail":"https://pica.zhimg.com/80/v2-719fb08680b14407d41a85d3ac8982f1_1440w.png"}]},{"type":"hot_list_feed","style_type":"1","id":"41_1658762809.653107","card_id":"Q_532200191","target":{"id":532200191,"title":"为什么有人感觉国足踢球我上我也行？","url":"https://api.zhihu.com/questions/532200191","type":"question","created":1652193470,"answer_count":691,"follower_count":784,"author":{"type":"people","user_type":"people","id":"0","url_token":"","url":"","name":"用户","headline":"","avatar_url":"https://pica.zhimg.com/aadd7b895_s.jpg"},"bound_topic_ids":[1811,2955,103878],"comment_count":33,"is_following":false,"excerpt":""},"attached_info":"Cj8Im4Pz3NOd09xaEAMaCDgwNTQ4NTI2IL7x6ZMGMCE4kAZAKXIJNTMyMjAwMTkxeACqAQliaWxsYm9hcmTSAQA=","detail_text":"40 万热度","trend":0,"debut":false,"children":[{"type":"answer","thumbnail":""}]},{"type":"hot_list_feed","style_type":"1","id":"42_1658762809.653431","card_id":"Q_544871109","target":{"id":544871109,"title":"饶毅炮轰华大集团 CEO 尹烨「哗众取宠伪科学」，尹烨回应「谢谢指教」，他的科普水平如何?","url":"https://api.zhihu.com/questions/544871109","type":"question","created":1658542422,"answer_count":82,"follower_count":267,"author":{"type":"people","user_type":"people","id":"0","url_token":"","url":"","name":"用户","headline":"","avatar_url":"https://pica.zhimg.com/aadd7b895_s.jpg"},"bound_topic_ids":[307,458,1309,58679,1908132],"comment_count":6,"is_following":false,"excerpt":"尹烨回应：谢谢指教。一如之前，我在《圆桌派》所表达的：三人行，必有我师焉。 关于饶毅教授评点本人科普工作的回应 最近某个企业的高管尹烨，本身生物的背景就比较局限，而且非常不严谨，有相当多故意哗众取宠的内容。他有关生物的演讲就有很多伪科学，而超出生物涉及其他科学，就错误百出。外行、特别是文科的听众被其吸引。如果他在国际大企业工作，早就因为损害企业声誉而被开除。 该企业早期的杨焕明确实是基础太差，不懂遗传学。一般人把基因测序与遗传学紧密联系而不知道两者在智力上的差别。生物学鸡鸭猫狗都可以看懂测序结果，但理解遗传学要求就高一些。我以前估计过杨焕明可能考不及格现在高中遗传学部分。但外界不了解，以为杨焕明真是专家，他也希望扮演科学家，所以回答问题出错。杨焕明后来知道藏拙。 与杨焕明因为扮演科学家而被动说错一些科学问题不一样，尹烨主动出来大范围忽悠就比较奇怪。尹烨的行为无异于主动说谎。他忽悠、胡说和欺骗的内容超出生命科学范围。批评他是为了破除人们误认为企业高管就可以随心所欲宣传伪科学。 摘自饶议科学公众号 信、达、雅：说起来容易 做起来..."},"attached_info":"Cj8Im4Pz3NOd09xaEAMaCDgzMzY1MTU1INay7ZYGMAY4iwJAKnIJNTQ0ODcxMTA5eACqAQliaWxsYm9hcmTSAQA=","detail_text":"40 万热度","trend":0,"debut":false,"children":[{"type":"answer","thumbnail":"https://pic1.zhimg.com/80/v2-d3d0f1d4b97d4d713c58c03183166287_1440w.jpg?source=1940ef5c"}]},{"type":"hot_list_feed","style_type":"1","id":"43_1658762809.6541874","card_id":"Q_540642555","target":{"id":540642555,"title":"《海贼王》是从什么时候诞生出四皇比大将强的结论的呢？","url":"https://api.zhihu.com/questions/540642555","type":"question","created":1656514257,"answer_count":54,"follower_count":63,"author":{"type":"people","user_type":"people","id":"0","url_token":"","url":"","name":"用户","headline":"","avatar_url":"https://pica.zhimg.com/aadd7b895_s.jpg"},"bound_topic_ids":[392,48237,211399],"comment_count":8,"is_following":false,"excerpt":"四皇一顿操作猛如虎，一看伤害2.5."},"attached_info":"Cj4Im4Pz3NOd09xaEAMaCDgyNDI0Njg2INHN8ZUGMAg4P0Arcgk1NDA2NDI1NTV4AKoBCWJpbGxib2FyZNIBAA==","detail_text":"40 万热度","trend":0,"debut":false,"children":[{"type":"answer","thumbnail":"https://pic1.zhimg.com/80/v2-629f8b0019641091534515d011a32df0_1440w.jpg?source=1940ef5c"}]},{"type":"hot_list_feed","style_type":"1","id":"44_1658762809.6548707","card_id":"Q_545109826","target":{"id":545109826,"title":"16 岁男生喝珍珠奶茶疑因呛到气管死亡，蜜雪冰城回应「会核实调查」，如何避免此类意外发生？","url":"https://api.zhihu.com/questions/545109826","type":"question","created":1658675070,"answer_count":14,"follower_count":38,"author":{"type":"people","user_type":"people","id":"0","url_token":"","url":"","name":"用户","headline":"","avatar_url":"https://pica.zhimg.com/aadd7b895_s.jpg"},"bound_topic_ids":[237,4800,5582,33765,267743],"comment_count":2,"is_following":false,"excerpt":"据红星新闻报道，事件发生于7月24日上午10时左右。当日晚上7时许，医院相关负责人告诉红星新闻，“120”赶到现场时，小伙便没了生命体征，接回医院重症监护室，也没有抢救回来。“原因应该是珍珠奶茶呛到气管里去了。”该负责人还透露，小伙年仅16岁。 25日上午，九派新闻联系四川蜜雪冰城餐饮管理有限公司，工作人员表示，尚不知晓此事，没有接到任何投诉，也没有接到分店的反馈。之后，公司会派区域经理负责核查。若事件属实，区域经理和公司会进行解决。 当日下午，四川蜜雪冰城餐饮管理有限公司另一工作人员称，“目前没有证据表明是因为喝了我们家的奶茶被卡喉。”其表示，如果珍珠尺寸存在问题，需要整个行业进行调整，并非蜜雪冰城一家的问题。 随后，九派新闻联系蜜雪冰城（政府西路店），工作人员称昨日未在店内，不清楚此事，门店仍在正常运营。 16岁男生喝珍珠奶茶疑因呛到气管死亡# 生活中，无论婴幼儿还是成人，都有可能面临异物卡喉窒息的危险。遇到这种情况怎么办？用海姆立克急救法！南京市急救中心工作人员演示不同年龄的正确施救措施↓扩散，让更多人看到！四川一小伙喝奶茶被卡喉？医院：未抢救过来，应是珍珠奶茶呛到气管里了-上游新闻 汇聚向上的力量"},"attached_info":"ClQIm4Pz3NOd09xaEAMaCDgzNDE4MjA5IP6+9ZYGMAI4JkAscgk1NDUxMDk4MjZ4AKoBCWJpbGxib2FyZNIBAPIBEwgBEg9kb21haW5fb3BlcmF0b3I=","detail_text":"40 万热度","trend":0,"debut":false,"children":[{"type":"answer","thumbnail":"https://pic2.zhimg.com/50/v2-6f2672921d2a2f1a5e2469b632879e8e_b.jpg"}]},{"type":"hot_list_feed","style_type":"1","id":"45_1658762809.6555936","card_id":"Q_544379342","target":{"id":544379342,"title":"在你心中，最能代表你「小时候的味道」的食物是什么？","url":"https://api.zhihu.com/questions/544379342","type":"question","created":1658311567,"answer_count":74,"follower_count":97,"author":{"type":"people","user_type":"people","id":"0","url_token":"","url":"","name":"用户","headline":"","avatar_url":"https://pica.zhimg.com/aadd7b895_s.jpg"},"bound_topic_ids":[304,617,740,2171,3352],"comment_count":1,"is_following":false,"excerpt":""},"attached_info":"Cj4Im4Pz3NOd09xaEAMaCDgzMjU1NjI3II+n35YGMAE4YUAtcgk1NDQzNzkzNDJ4AKoBCWJpbGxib2FyZNIBAA==","detail_text":"40 万热度","trend":0,"debut":false,"children":[{"type":"answer","thumbnail":"https://pic1.zhimg.com/80/v2-20f554c85e3c8c69ed223b478aa3fac5_1440w.jpg?source=1940ef5c"}]},{"type":"hot_list_feed","style_type":"1","id":"46_1658762809.656106","card_id":"Q_286816625","target":{"id":286816625,"title":"大家怎样看待身边的学人精？","url":"https://api.zhihu.com/questions/286816625","type":"question","created":1532493010,"answer_count":390,"follower_count":790,"author":{"type":"people","user_type":"people","id":"0","url_token":"","url":"","name":"用户","headline":"","avatar_url":"https://pica.zhimg.com/aadd7b895_s.jpg"},"bound_topic_ids":[1532,8291],"comment_count":11,"is_following":false,"excerpt":""},"attached_info":"Cj8Im4Pz3NOd09xaEAMaCDI2MDE0MDg0INL539oFMAs4lgZALnIJMjg2ODE2NjI1eACqAQliaWxsYm9hcmTSAQA=","detail_text":"39 万热度","trend":0,"debut":false,"children":[{"type":"answer","thumbnail":"https://pic1.zhimg.com/50/v2-f6b43a9ad70e43c654ef5cb76bca4cae_b.jpg"}]},{"type":"hot_list_feed","style_type":"1","id":"47_1658762809.6564913","card_id":"Q_545088820","target":{"id":545088820,"title":"游戏的繁体翻译水平是否高于简体？为什么？","url":"https://api.zhihu.com/questions/545088820","type":"question","created":1658665535,"answer_count":76,"follower_count":107,"author":{"type":"people","user_type":"people","id":"0","url_token":"","url":"","name":"用户","headline":"","avatar_url":"https://pica.zhimg.com/aadd7b895_s.jpg"},"bound_topic_ids":[253,642,1172,1314,98130],"comment_count":10,"is_following":false,"excerpt":""},"attached_info":"Cj4Im4Pz3NOd09xaEAMaCDgzNDEzNTcwIL/09JYGMAo4a0Avcgk1NDUwODg4MjB4AKoBCWJpbGxib2FyZNIBAA==","detail_text":"39 万热度","trend":0,"debut":false,"children":[{"type":"answer","thumbnail":"https://pic2.zhimg.com/80/v2-9f2e96eecd0f897c853823cddb97ed94_1440w.jpg?source=1940ef5c"}]},{"type":"hot_list_feed","style_type":"1","id":"48_1658762809.656965","card_id":"Q_27486818","target":{"id":27486818,"title":"哪些法律上的小常识可以保护自己？","url":"https://api.zhihu.com/questions/27486818","type":"question","created":1420772618,"answer_count":804,"follower_count":120911,"author":{"type":"people","user_type":"people","id":"0","url_token":"","url":"","name":"用户","headline":"","avatar_url":"https://pica.zhimg.com/aadd7b895_s.jpg"},"bound_topic_ids":[215,6551,7576,10167,31665],"comment_count":35,"is_following":false,"excerpt":"不懂法的人太多了，有哪些必须知道的法律用来保护自己呢？"},"attached_info":"Cj4Im4Pz3NOd09xaEAMaBzMxNzc1NTAgioq9pQUwIzjPsAdAMHIIMjc0ODY4MTh4AKoBCWJpbGxib2FyZNIBAA==","detail_text":"38 万热度","trend":0,"debut":false,"children":[{"type":"answer","thumbnail":"https://pic1.zhimg.com/80/v2-e4cc7b96ae5cc7011c768110124c1b7d_1440w.jpg?source=1940ef5c"}]},{"type":"hot_list_feed","style_type":"1","id":"49_1658762809.657451","card_id":"Q_25403694","target":{"id":25403694,"title":"为什么说光速不能被超越？","url":"https://api.zhihu.com/questions/25403694","type":"question","created":1410971965,"answer_count":462,"follower_count":3567,"author":{"type":"people","user_type":"people","id":"0","url_token":"","url":"","name":"用户","headline":"","avatar_url":"https://pica.zhimg.com/aadd7b895_s.jpg"},"bound_topic_ids":[2253,4663,6432],"comment_count":29,"is_following":false,"excerpt":"为什么说光速不能被超越？如果假设有艘和光速一样快的飞船，而我就在飞船里沿着飞船前进的方向跑，那我前进的速度对于地面上的人来说不就是飞船的速度+我跑步的速度＞光速。提的问题可能有点无知，但我真的想不通。"},"attached_info":"Cj0Im4Pz3NOd09xaEAMaBzIzNDQxMjEgvfLmoAUwHTjvG0AxcggyNTQwMzY5NHgAqgEJYmlsbGJvYXJk0gEA","detail_text":"38 万热度","trend":0,"debut":false,"children":[{"type":"answer","thumbnail":"https://pic2.zhimg.com/80/v2-291bdaf56b529e4dc5238883af46bd36_1440w.png"}]}],"description":{"time":"2022-07-25 23:26:49"}}